<?xml version="1.0" encoding="UTF-8" standalone="yes"?>
<ns3:mets xmlns:ns2="http://www.w3.org/1999/xlink" xmlns:ns3="http://www.loc.gov/METS/" xmlns:xsi="http://www.w3.org/2001/XMLSchema-instance" OBJID="772836" LABEL="B III 459" PROFILE="TRP_V1" xsi:schemaLocation="http://www.loc.gov/METS/ http://www.loc.gov/standards/mets/mets.xsd">
    <ns3:metsHdr CREATEDATE="2023-06-23T12:08:26.427+02:00" LASTMODDATE="2023-06-23T12:08:26.427+02:00" RECORDSTATUS="SUBMITTED">
        <ns3:agent ROLE="CREATOR" TYPE="ORGANIZATION">
            <ns3:name>UIBK</ns3:name>
            <ns3:note>This METS file was generated by Transkribus</ns3:note>
        </ns3:agent>
    </ns3:metsHdr>
    <ns3:amdSec ID="SOURCE">
        <ns3:sourceMD ID="MD_ORIG">
            <ns3:mdWrap ID="TRP_DOC_MD" MDTYPE="OTHER">
                <ns3:xmlData>
                    <trpDocMetadata>
                        <docId>772836</docId>
                        <title>B III 459</title>
                        <uploadTimestamp>1630840092457</uploadTimestamp>
                        <uploader>christa.schneider@wbkolleg.unibe.ch</uploader>
                        <uploaderId>68050</uploaderId>
                        <nrOfPages>106</nrOfPages>
                        <pageId>29283268</pageId>
                        <url>https://files.transkribus.eu/Get?fileType=view&amp;id=CYVHPHPKDUHLNCXIQHEJPAXD</url>
                        <thumbUrl>https://files.transkribus.eu/Get?fileType=thumb&amp;id=CYVHPHPKDUHLNCXIQHEJPAXD</thumbUrl>
                        <externalId>NA</externalId>
                        <authority>NA</authority>
                        <status>0</status>
                        <fimgStoreColl>TrpDoc_DEA_772836</fimgStoreColl>
                        <localFolder>/mnt/transkribus/export/TRP_EXPORT_3377186889189622108/772836/B_III_459</localFolder>
                        <origDocId>0</origDocId>
                        <collectionList>
                            <colList>
<colId>112481</colId>
<colName>StABE_Chorgerichtsmanuale</colName>
<description>created by christa.schneider@wbkolleg.unibe.ch</description>
<crowdsourcing>false</crowdsourcing>
<elearning>false</elearning>
<nrOfDocuments>0</nrOfDocuments>
                            </colList>
                        </collectionList>
                    </trpDocMetadata>
                </ns3:xmlData>
            </ns3:mdWrap>
        </ns3:sourceMD>
    </ns3:amdSec>
    <ns3:fileSec>
        <ns3:fileGrp ID="MASTER">
            <ns3:fileGrp ID="PAGEXML">
                <ns3:file ID="PAGEXML_1" SEQ="1" MIMETYPE="application/xml" CREATED="2023-06-23T12:08:12.000+02:00" CHECKSUM="b94a2828f14d3d016386276027e1fcdc" CHECKSUMTYPE="MD5">
                    <ns3:FLocat LOCTYPE="OTHER" OTHERLOCTYPE="FILE" ns2:type="simple" ns2:href="page/IMG_4190.xml"/>
                </ns3:file>
                <ns3:file ID="PAGEXML_2" SEQ="2" MIMETYPE="application/xml" CREATED="2023-06-23T12:08:12.000+02:00" CHECKSUM="9f6e6b750b81898d3e81000f51096dfd" CHECKSUMTYPE="MD5">
                    <ns3:FLocat LOCTYPE="OTHER" OTHERLOCTYPE="FILE" ns2:type="simple" ns2:href="page/IMG_4191.xml"/>
                </ns3:file>
                <ns3:file ID="PAGEXML_3" SEQ="3" MIMETYPE="application/xml" CREATED="2023-06-23T12:08:13.000+02:00" CHECKSUM="4f2991a7daf4059e43adea159634e9ef" CHECKSUMTYPE="MD5">
                    <ns3:FLocat LOCTYPE="OTHER" OTHERLOCTYPE="FILE" ns2:type="simple" ns2:href="page/IMG_4192.xml"/>
                </ns3:file>
                <ns3:file ID="PAGEXML_4" SEQ="4" MIMETYPE="application/xml" CREATED="2023-06-23T12:08:13.000+02:00" CHECKSUM="d314793021ccdfbe70e8df0d4c42247b" CHECKSUMTYPE="MD5">
                    <ns3:FLocat LOCTYPE="OTHER" OTHERLOCTYPE="FILE" ns2:type="simple" ns2:href="page/IMG_4193.xml"/>
                </ns3:file>
                <ns3:file ID="PAGEXML_5" SEQ="5" MIMETYPE="application/xml" CREATED="2023-06-23T12:08:13.000+02:00" CHECKSUM="d2c82f794a6a6ea364be590b74683865" CHECKSUMTYPE="MD5">
                    <ns3:FLocat LOCTYPE="OTHER" OTHERLOCTYPE="FILE" ns2:type="simple" ns2:href="page/IMG_4194.xml"/>
                </ns3:file>
                <ns3:file ID="PAGEXML_6" SEQ="6" MIMETYPE="application/xml" CREATED="2023-06-23T12:08:13.000+02:00" CHECKSUM="e6c786b7b2726429dd63859248452065" CHECKSUMTYPE="MD5">
                    <ns3:FLocat LOCTYPE="OTHER" OTHERLOCTYPE="FILE" ns2:type="simple" ns2:href="page/IMG_4195.xml"/>
                </ns3:file>
                <ns3:file ID="PAGEXML_7" SEQ="7" MIMETYPE="application/xml" CREATED="2023-06-23T12:08:13.000+02:00" CHECKSUM="cf2a355b9314cac0172faa65b3459e54" CHECKSUMTYPE="MD5">
                    <ns3:FLocat LOCTYPE="OTHER" OTHERLOCTYPE="FILE" ns2:type="simple" ns2:href="page/IMG_4196.xml"/>
                </ns3:file>
                <ns3:file ID="PAGEXML_8" SEQ="8" MIMETYPE="application/xml" CREATED="2023-06-23T12:08:13.000+02:00" CHECKSUM="662f300ea203e5780e6cc77a87771400" CHECKSUMTYPE="MD5">
                    <ns3:FLocat LOCTYPE="OTHER" OTHERLOCTYPE="FILE" ns2:type="simple" ns2:href="page/IMG_4197.xml"/>
                </ns3:file>
                <ns3:file ID="PAGEXML_9" SEQ="9" MIMETYPE="application/xml" CREATED="2023-06-23T12:08:13.000+02:00" CHECKSUM="0ed95480509bcf12473325727aec874f" CHECKSUMTYPE="MD5">
                    <ns3:FLocat LOCTYPE="OTHER" OTHERLOCTYPE="FILE" ns2:type="simple" ns2:href="page/IMG_4198.xml"/>
                </ns3:file>
                <ns3:file ID="PAGEXML_10" SEQ="10" MIMETYPE="application/xml" CREATED="2023-06-23T12:08:13.000+02:00" CHECKSUM="e6082a908aff2dddf764b70e67279c5f" CHECKSUMTYPE="MD5">
                    <ns3:FLocat LOCTYPE="OTHER" OTHERLOCTYPE="FILE" ns2:type="simple" ns2:href="page/IMG_4199.xml"/>
                </ns3:file>
                <ns3:file ID="PAGEXML_11" SEQ="11" MIMETYPE="application/xml" CREATED="2023-06-23T12:08:14.000+02:00" CHECKSUM="d920e6cd019a71e79d30965300320556" CHECKSUMTYPE="MD5">
                    <ns3:FLocat LOCTYPE="OTHER" OTHERLOCTYPE="FILE" ns2:type="simple" ns2:href="page/IMG_4200.xml"/>
                </ns3:file>
                <ns3:file ID="PAGEXML_12" SEQ="12" MIMETYPE="application/xml" CREATED="2023-06-23T12:08:14.000+02:00" CHECKSUM="7721276fa31efb3357bac1f032ac9fd6" CHECKSUMTYPE="MD5">
                    <ns3:FLocat LOCTYPE="OTHER" OTHERLOCTYPE="FILE" ns2:type="simple" ns2:href="page/IMG_4201.xml"/>
                </ns3:file>
                <ns3:file ID="PAGEXML_13" SEQ="13" MIMETYPE="application/xml" CREATED="2023-06-23T12:08:14.000+02:00" CHECKSUM="affafc6c6224225cde83e3deec9d7f6a" CHECKSUMTYPE="MD5">
                    <ns3:FLocat LOCTYPE="OTHER" OTHERLOCTYPE="FILE" ns2:type="simple" ns2:href="page/IMG_4202.xml"/>
                </ns3:file>
                <ns3:file ID="PAGEXML_14" SEQ="14" MIMETYPE="application/xml" CREATED="2023-06-23T12:08:14.000+02:00" CHECKSUM="a338bef719a8d9e592d38385d5016355" CHECKSUMTYPE="MD5">
                    <ns3:FLocat LOCTYPE="OTHER" OTHERLOCTYPE="FILE" ns2:type="simple" ns2:href="page/IMG_4203.xml"/>
                </ns3:file>
                <ns3:file ID="PAGEXML_15" SEQ="15" MIMETYPE="application/xml" CREATED="2023-06-23T12:08:14.000+02:00" CHECKSUM="6d386ffac62f6a96ba16ab0d3f818072" CHECKSUMTYPE="MD5">
                    <ns3:FLocat LOCTYPE="OTHER" OTHERLOCTYPE="FILE" ns2:type="simple" ns2:href="page/IMG_4204.xml"/>
                </ns3:file>
                <ns3:file ID="PAGEXML_16" SEQ="16" MIMETYPE="application/xml" CREATED="2023-06-23T12:08:14.000+02:00" CHECKSUM="30138b9af9bcf99e34b6dbc6ac317d8f" CHECKSUMTYPE="MD5">
                    <ns3:FLocat LOCTYPE="OTHER" OTHERLOCTYPE="FILE" ns2:type="simple" ns2:href="page/IMG_4205.xml"/>
                </ns3:file>
                <ns3:file ID="PAGEXML_17" SEQ="17" MIMETYPE="application/xml" CREATED="2023-06-23T12:08:14.000+02:00" CHECKSUM="904fdf750b4c648e8aab3ce2a40b8a29" CHECKSUMTYPE="MD5">
                    <ns3:FLocat LOCTYPE="OTHER" OTHERLOCTYPE="FILE" ns2:type="simple" ns2:href="page/IMG_4206.xml"/>
                </ns3:file>
                <ns3:file ID="PAGEXML_18" SEQ="18" MIMETYPE="application/xml" CREATED="2023-06-23T12:08:14.000+02:00" CHECKSUM="4dee2b9e670d0119a0956265576d5120" CHECKSUMTYPE="MD5">
                    <ns3:FLocat LOCTYPE="OTHER" OTHERLOCTYPE="FILE" ns2:type="simple" ns2:href="page/IMG_4207.xml"/>
                </ns3:file>
                <ns3:file ID="PAGEXML_19" SEQ="19" MIMETYPE="application/xml" CREATED="2023-06-23T12:08:14.000+02:00" CHECKSUM="2078f1e9e4a19af5fe54dadee63de9c0" CHECKSUMTYPE="MD5">
                    <ns3:FLocat LOCTYPE="OTHER" OTHERLOCTYPE="FILE" ns2:type="simple" ns2:href="page/IMG_4208.xml"/>
                </ns3:file>
                <ns3:file ID="PAGEXML_20" SEQ="20" MIMETYPE="application/xml" CREATED="2023-06-23T12:08:15.000+02:00" CHECKSUM="8adb01f54a0de06c462dc58b20fd0ff5" CHECKSUMTYPE="MD5">
                    <ns3:FLocat LOCTYPE="OTHER" OTHERLOCTYPE="FILE" ns2:type="simple" ns2:href="page/IMG_4209.xml"/>
                </ns3:file>
                <ns3:file ID="PAGEXML_21" SEQ="21" MIMETYPE="application/xml" CREATED="2023-06-23T12:08:15.000+02:00" CHECKSUM="75506247696a9d3dc1d763f694d9ca86" CHECKSUMTYPE="MD5">
                    <ns3:FLocat LOCTYPE="OTHER" OTHERLOCTYPE="FILE" ns2:type="simple" ns2:href="page/IMG_4210.xml"/>
                </ns3:file>
                <ns3:file ID="PAGEXML_22" SEQ="22" MIMETYPE="application/xml" CREATED="2023-06-23T12:08:15.000+02:00" CHECKSUM="fdfe7d207372cc8bd67bb6d6f8c735ce" CHECKSUMTYPE="MD5">
                    <ns3:FLocat LOCTYPE="OTHER" OTHERLOCTYPE="FILE" ns2:type="simple" ns2:href="page/IMG_4211.xml"/>
                </ns3:file>
                <ns3:file ID="PAGEXML_23" SEQ="23" MIMETYPE="application/xml" CREATED="2023-06-23T12:08:15.000+02:00" CHECKSUM="1d38ec9226e406ab0f0c4f99a61f4bd5" CHECKSUMTYPE="MD5">
                    <ns3:FLocat LOCTYPE="OTHER" OTHERLOCTYPE="FILE" ns2:type="simple" ns2:href="page/IMG_4212.xml"/>
                </ns3:file>
                <ns3:file ID="PAGEXML_24" SEQ="24" MIMETYPE="application/xml" CREATED="2023-06-23T12:08:15.000+02:00" CHECKSUM="c1be13029f69baa08e5787210e098778" CHECKSUMTYPE="MD5">
                    <ns3:FLocat LOCTYPE="OTHER" OTHERLOCTYPE="FILE" ns2:type="simple" ns2:href="page/IMG_4213.xml"/>
                </ns3:file>
                <ns3:file ID="PAGEXML_25" SEQ="25" MIMETYPE="application/xml" CREATED="2023-06-23T12:08:15.000+02:00" CHECKSUM="7cb52d558c40d915cad574d997b13e56" CHECKSUMTYPE="MD5">
                    <ns3:FLocat LOCTYPE="OTHER" OTHERLOCTYPE="FILE" ns2:type="simple" ns2:href="page/IMG_4214.xml"/>
                </ns3:file>
                <ns3:file ID="PAGEXML_26" SEQ="26" MIMETYPE="application/xml" CREATED="2023-06-23T12:08:15.000+02:00" CHECKSUM="1fdb5430c53a96d93a77acea2fde21e4" CHECKSUMTYPE="MD5">
                    <ns3:FLocat LOCTYPE="OTHER" OTHERLOCTYPE="FILE" ns2:type="simple" ns2:href="page/IMG_4215.xml"/>
                </ns3:file>
                <ns3:file ID="PAGEXML_27" SEQ="27" MIMETYPE="application/xml" CREATED="2023-06-23T12:08:16.000+02:00" CHECKSUM="428ca33e8a6ab9ae94f2ecd6cceae282" CHECKSUMTYPE="MD5">
                    <ns3:FLocat LOCTYPE="OTHER" OTHERLOCTYPE="FILE" ns2:type="simple" ns2:href="page/IMG_4216.xml"/>
                </ns3:file>
                <ns3:file ID="PAGEXML_28" SEQ="28" MIMETYPE="application/xml" CREATED="2023-06-23T12:08:16.000+02:00" CHECKSUM="e20cbc88efcc0f84dddb726b6cfd0aa2" CHECKSUMTYPE="MD5">
                    <ns3:FLocat LOCTYPE="OTHER" OTHERLOCTYPE="FILE" ns2:type="simple" ns2:href="page/IMG_4217.xml"/>
                </ns3:file>
                <ns3:file ID="PAGEXML_29" SEQ="29" MIMETYPE="application/xml" CREATED="2023-06-23T12:08:16.000+02:00" CHECKSUM="89f5f8b7a619c6165584c6f7fcd6b283" CHECKSUMTYPE="MD5">
                    <ns3:FLocat LOCTYPE="OTHER" OTHERLOCTYPE="FILE" ns2:type="simple" ns2:href="page/IMG_4218.xml"/>
                </ns3:file>
                <ns3:file ID="PAGEXML_30" SEQ="30" MIMETYPE="application/xml" CREATED="2023-06-23T12:08:16.000+02:00" CHECKSUM="bec98e6f03676d11e9be97981c496aac" CHECKSUMTYPE="MD5">
                    <ns3:FLocat LOCTYPE="OTHER" OTHERLOCTYPE="FILE" ns2:type="simple" ns2:href="page/IMG_4219.xml"/>
                </ns3:file>
                <ns3:file ID="PAGEXML_31" SEQ="31" MIMETYPE="application/xml" CREATED="2023-06-23T12:08:16.000+02:00" CHECKSUM="5ac5fce670b5a103a9bb631d720365ba" CHECKSUMTYPE="MD5">
                    <ns3:FLocat LOCTYPE="OTHER" OTHERLOCTYPE="FILE" ns2:type="simple" ns2:href="page/IMG_4220.xml"/>
                </ns3:file>
                <ns3:file ID="PAGEXML_32" SEQ="32" MIMETYPE="application/xml" CREATED="2023-06-23T12:08:16.000+02:00" CHECKSUM="c18cd976eddabaa872ca99565a344f0c" CHECKSUMTYPE="MD5">
                    <ns3:FLocat LOCTYPE="OTHER" OTHERLOCTYPE="FILE" ns2:type="simple" ns2:href="page/IMG_4221.xml"/>
                </ns3:file>
                <ns3:file ID="PAGEXML_33" SEQ="33" MIMETYPE="application/xml" CREATED="2023-06-23T12:08:16.000+02:00" CHECKSUM="97950b2f7d1c04153718b507397cc330" CHECKSUMTYPE="MD5">
                    <ns3:FLocat LOCTYPE="OTHER" OTHERLOCTYPE="FILE" ns2:type="simple" ns2:href="page/IMG_4222.xml"/>
                </ns3:file>
                <ns3:file ID="PAGEXML_34" SEQ="34" MIMETYPE="application/xml" CREATED="2023-06-23T12:08:16.000+02:00" CHECKSUM="bf91c103c48e15a54d8e43f90c741dd6" CHECKSUMTYPE="MD5">
                    <ns3:FLocat LOCTYPE="OTHER" OTHERLOCTYPE="FILE" ns2:type="simple" ns2:href="page/IMG_4223.xml"/>
                </ns3:file>
                <ns3:file ID="PAGEXML_35" SEQ="35" MIMETYPE="application/xml" CREATED="2023-06-23T12:08:16.000+02:00" CHECKSUM="b5fbfa65dccccf04d0146365c08bad32" CHECKSUMTYPE="MD5">
                    <ns3:FLocat LOCTYPE="OTHER" OTHERLOCTYPE="FILE" ns2:type="simple" ns2:href="page/IMG_4224.xml"/>
                </ns3:file>
                <ns3:file ID="PAGEXML_36" SEQ="36" MIMETYPE="application/xml" CREATED="2023-06-23T12:08:16.000+02:00" CHECKSUM="3d8b0c178b251a8c4c49928f61026f2e" CHECKSUMTYPE="MD5">
                    <ns3:FLocat LOCTYPE="OTHER" OTHERLOCTYPE="FILE" ns2:type="simple" ns2:href="page/IMG_4225.xml"/>
                </ns3:file>
                <ns3:file ID="PAGEXML_37" SEQ="37" MIMETYPE="application/xml" CREATED="2023-06-23T12:08:18.000+02:00" CHECKSUM="9264e04d20aec855c0246962bd6f4e2e" CHECKSUMTYPE="MD5">
                    <ns3:FLocat LOCTYPE="OTHER" OTHERLOCTYPE="FILE" ns2:type="simple" ns2:href="page/IMG_4226.xml"/>
                </ns3:file>
                <ns3:file ID="PAGEXML_38" SEQ="38" MIMETYPE="application/xml" CREATED="2023-06-23T12:08:18.000+02:00" CHECKSUM="5d1835faa40c3a624c79ba23ed58f8ad" CHECKSUMTYPE="MD5">
                    <ns3:FLocat LOCTYPE="OTHER" OTHERLOCTYPE="FILE" ns2:type="simple" ns2:href="page/IMG_4227.xml"/>
                </ns3:file>
                <ns3:file ID="PAGEXML_39" SEQ="39" MIMETYPE="application/xml" CREATED="2023-06-23T12:08:18.000+02:00" CHECKSUM="23103b4a2cdc9385b1fc5645b2e9e3fb" CHECKSUMTYPE="MD5">
                    <ns3:FLocat LOCTYPE="OTHER" OTHERLOCTYPE="FILE" ns2:type="simple" ns2:href="page/IMG_4228.xml"/>
                </ns3:file>
                <ns3:file ID="PAGEXML_40" SEQ="40" MIMETYPE="application/xml" CREATED="2023-06-23T12:08:18.000+02:00" CHECKSUM="9fcccc1c5b060da0ca198fc9359add15" CHECKSUMTYPE="MD5">
                    <ns3:FLocat LOCTYPE="OTHER" OTHERLOCTYPE="FILE" ns2:type="simple" ns2:href="page/IMG_4229.xml"/>
                </ns3:file>
                <ns3:file ID="PAGEXML_41" SEQ="41" MIMETYPE="application/xml" CREATED="2023-06-23T12:08:19.000+02:00" CHECKSUM="3930c95c0aa29578d1e28aa23e349e5d" CHECKSUMTYPE="MD5">
                    <ns3:FLocat LOCTYPE="OTHER" OTHERLOCTYPE="FILE" ns2:type="simple" ns2:href="page/IMG_4230.xml"/>
                </ns3:file>
                <ns3:file ID="PAGEXML_42" SEQ="42" MIMETYPE="application/xml" CREATED="2023-06-23T12:08:19.000+02:00" CHECKSUM="d510f9dd933a4a86efe879c7c88b03e6" CHECKSUMTYPE="MD5">
                    <ns3:FLocat LOCTYPE="OTHER" OTHERLOCTYPE="FILE" ns2:type="simple" ns2:href="page/IMG_4231.xml"/>
                </ns3:file>
                <ns3:file ID="PAGEXML_43" SEQ="43" MIMETYPE="application/xml" CREATED="2023-06-23T12:08:19.000+02:00" CHECKSUM="e0809ee74d1cc64b20f2f74fa2179410" CHECKSUMTYPE="MD5">
                    <ns3:FLocat LOCTYPE="OTHER" OTHERLOCTYPE="FILE" ns2:type="simple" ns2:href="page/IMG_4232.xml"/>
                </ns3:file>
                <ns3:file ID="PAGEXML_44" SEQ="44" MIMETYPE="application/xml" CREATED="2023-06-23T12:08:19.000+02:00" CHECKSUM="b78aa4d9866638ce3353011af29e7232" CHECKSUMTYPE="MD5">
                    <ns3:FLocat LOCTYPE="OTHER" OTHERLOCTYPE="FILE" ns2:type="simple" ns2:href="page/IMG_4233.xml"/>
                </ns3:file>
                <ns3:file ID="PAGEXML_45" SEQ="45" MIMETYPE="application/xml" CREATED="2023-06-23T12:08:19.000+02:00" CHECKSUM="98c978f65298491412d1f20eb09c7974" CHECKSUMTYPE="MD5">
                    <ns3:FLocat LOCTYPE="OTHER" OTHERLOCTYPE="FILE" ns2:type="simple" ns2:href="page/IMG_4234.xml"/>
                </ns3:file>
                <ns3:file ID="PAGEXML_46" SEQ="46" MIMETYPE="application/xml" CREATED="2023-06-23T12:08:19.000+02:00" CHECKSUM="d452bb054437491e90e6c555e2a4a200" CHECKSUMTYPE="MD5">
                    <ns3:FLocat LOCTYPE="OTHER" OTHERLOCTYPE="FILE" ns2:type="simple" ns2:href="page/IMG_4235.xml"/>
                </ns3:file>
                <ns3:file ID="PAGEXML_47" SEQ="47" MIMETYPE="application/xml" CREATED="2023-06-23T12:08:19.000+02:00" CHECKSUM="0350f3226c87ad89daba47974eb33800" CHECKSUMTYPE="MD5">
                    <ns3:FLocat LOCTYPE="OTHER" OTHERLOCTYPE="FILE" ns2:type="simple" ns2:href="page/IMG_4236.xml"/>
                </ns3:file>
                <ns3:file ID="PAGEXML_48" SEQ="48" MIMETYPE="application/xml" CREATED="2023-06-23T12:08:19.000+02:00" CHECKSUM="52effbe8548176428ede44a02c8d7e07" CHECKSUMTYPE="MD5">
                    <ns3:FLocat LOCTYPE="OTHER" OTHERLOCTYPE="FILE" ns2:type="simple" ns2:href="page/IMG_4237.xml"/>
                </ns3:file>
                <ns3:file ID="PAGEXML_49" SEQ="49" MIMETYPE="application/xml" CREATED="2023-06-23T12:08:19.000+02:00" CHECKSUM="0ebcb96b2071cee668ba476b30114f21" CHECKSUMTYPE="MD5">
                    <ns3:FLocat LOCTYPE="OTHER" OTHERLOCTYPE="FILE" ns2:type="simple" ns2:href="page/IMG_4238.xml"/>
                </ns3:file>
                <ns3:file ID="PAGEXML_50" SEQ="50" MIMETYPE="application/xml" CREATED="2023-06-23T12:08:20.000+02:00" CHECKSUM="e3fdf26496cf3323e8e2178fe1a2ff1d" CHECKSUMTYPE="MD5">
                    <ns3:FLocat LOCTYPE="OTHER" OTHERLOCTYPE="FILE" ns2:type="simple" ns2:href="page/IMG_4239.xml"/>
                </ns3:file>
                <ns3:file ID="PAGEXML_51" SEQ="51" MIMETYPE="application/xml" CREATED="2023-06-23T12:08:20.000+02:00" CHECKSUM="f831f5093037cd92ef87f6aecf085c97" CHECKSUMTYPE="MD5">
                    <ns3:FLocat LOCTYPE="OTHER" OTHERLOCTYPE="FILE" ns2:type="simple" ns2:href="page/IMG_4240.xml"/>
                </ns3:file>
                <ns3:file ID="PAGEXML_52" SEQ="52" MIMETYPE="application/xml" CREATED="2023-06-23T12:08:20.000+02:00" CHECKSUM="ad6fcad3d6b31de9a61dbcc0a81317ca" CHECKSUMTYPE="MD5">
                    <ns3:FLocat LOCTYPE="OTHER" OTHERLOCTYPE="FILE" ns2:type="simple" ns2:href="page/IMG_4241.xml"/>
                </ns3:file>
                <ns3:file ID="PAGEXML_53" SEQ="53" MIMETYPE="application/xml" CREATED="2023-06-23T12:08:20.000+02:00" CHECKSUM="8facc0543c3c4d360112526acb3078b4" CHECKSUMTYPE="MD5">
                    <ns3:FLocat LOCTYPE="OTHER" OTHERLOCTYPE="FILE" ns2:type="simple" ns2:href="page/IMG_4242.xml"/>
                </ns3:file>
                <ns3:file ID="PAGEXML_54" SEQ="54" MIMETYPE="application/xml" CREATED="2023-06-23T12:08:20.000+02:00" CHECKSUM="8e1cce4366d3827b49325981c61b8459" CHECKSUMTYPE="MD5">
                    <ns3:FLocat LOCTYPE="OTHER" OTHERLOCTYPE="FILE" ns2:type="simple" ns2:href="page/IMG_4243.xml"/>
                </ns3:file>
                <ns3:file ID="PAGEXML_55" SEQ="55" MIMETYPE="application/xml" CREATED="2023-06-23T12:08:20.000+02:00" CHECKSUM="14b957cd6046b99b4e50f10c7d228a0f" CHECKSUMTYPE="MD5">
                    <ns3:FLocat LOCTYPE="OTHER" OTHERLOCTYPE="FILE" ns2:type="simple" ns2:href="page/IMG_4244.xml"/>
                </ns3:file>
                <ns3:file ID="PAGEXML_56" SEQ="56" MIMETYPE="application/xml" CREATED="2023-06-23T12:08:20.000+02:00" CHECKSUM="aa55e6f8a93d67899b556dc165b066fe" CHECKSUMTYPE="MD5">
                    <ns3:FLocat LOCTYPE="OTHER" OTHERLOCTYPE="FILE" ns2:type="simple" ns2:href="page/IMG_4245.xml"/>
                </ns3:file>
                <ns3:file ID="PAGEXML_57" SEQ="57" MIMETYPE="application/xml" CREATED="2023-06-23T12:08:20.000+02:00" CHECKSUM="0f79005127106bc85ce75b1bec9562bb" CHECKSUMTYPE="MD5">
                    <ns3:FLocat LOCTYPE="OTHER" OTHERLOCTYPE="FILE" ns2:type="simple" ns2:href="page/IMG_4246.xml"/>
                </ns3:file>
                <ns3:file ID="PAGEXML_58" SEQ="58" MIMETYPE="application/xml" CREATED="2023-06-23T12:08:20.000+02:00" CHECKSUM="6dbaf5a16b9bf7ef6160818e72af5ffe" CHECKSUMTYPE="MD5">
                    <ns3:FLocat LOCTYPE="OTHER" OTHERLOCTYPE="FILE" ns2:type="simple" ns2:href="page/IMG_4247.xml"/>
                </ns3:file>
                <ns3:file ID="PAGEXML_59" SEQ="59" MIMETYPE="application/xml" CREATED="2023-06-23T12:08:21.000+02:00" CHECKSUM="130225f48cc1bb6f3229eee0cbeb535f" CHECKSUMTYPE="MD5">
                    <ns3:FLocat LOCTYPE="OTHER" OTHERLOCTYPE="FILE" ns2:type="simple" ns2:href="page/IMG_4248.xml"/>
                </ns3:file>
                <ns3:file ID="PAGEXML_60" SEQ="60" MIMETYPE="application/xml" CREATED="2023-06-23T12:08:21.000+02:00" CHECKSUM="28921a0e6d83af228d3e17b4397e631a" CHECKSUMTYPE="MD5">
                    <ns3:FLocat LOCTYPE="OTHER" OTHERLOCTYPE="FILE" ns2:type="simple" ns2:href="page/IMG_4249.xml"/>
                </ns3:file>
                <ns3:file ID="PAGEXML_61" SEQ="61" MIMETYPE="application/xml" CREATED="2023-06-23T12:08:21.000+02:00" CHECKSUM="fb8e1671d82d2481ba6541554509b30e" CHECKSUMTYPE="MD5">
                    <ns3:FLocat LOCTYPE="OTHER" OTHERLOCTYPE="FILE" ns2:type="simple" ns2:href="page/IMG_4250.xml"/>
                </ns3:file>
                <ns3:file ID="PAGEXML_62" SEQ="62" MIMETYPE="application/xml" CREATED="2023-06-23T12:08:21.000+02:00" CHECKSUM="fb8e9008182418aedf858d9f24d9611f" CHECKSUMTYPE="MD5">
                    <ns3:FLocat LOCTYPE="OTHER" OTHERLOCTYPE="FILE" ns2:type="simple" ns2:href="page/IMG_4251.xml"/>
                </ns3:file>
                <ns3:file ID="PAGEXML_63" SEQ="63" MIMETYPE="application/xml" CREATED="2023-06-23T12:08:21.000+02:00" CHECKSUM="b2e6c6c70a81ca5251d28eb4c1b07840" CHECKSUMTYPE="MD5">
                    <ns3:FLocat LOCTYPE="OTHER" OTHERLOCTYPE="FILE" ns2:type="simple" ns2:href="page/IMG_4252.xml"/>
                </ns3:file>
                <ns3:file ID="PAGEXML_64" SEQ="64" MIMETYPE="application/xml" CREATED="2023-06-23T12:08:21.000+02:00" CHECKSUM="37a0dcd255dd961af5ccf9797cb99aad" CHECKSUMTYPE="MD5">
                    <ns3:FLocat LOCTYPE="OTHER" OTHERLOCTYPE="FILE" ns2:type="simple" ns2:href="page/IMG_4253.xml"/>
                </ns3:file>
                <ns3:file ID="PAGEXML_65" SEQ="65" MIMETYPE="application/xml" CREATED="2023-06-23T12:08:21.000+02:00" CHECKSUM="26b582e1074c2e124e7ef618c5210673" CHECKSUMTYPE="MD5">
                    <ns3:FLocat LOCTYPE="OTHER" OTHERLOCTYPE="FILE" ns2:type="simple" ns2:href="page/IMG_4254.xml"/>
                </ns3:file>
                <ns3:file ID="PAGEXML_66" SEQ="66" MIMETYPE="application/xml" CREATED="2023-06-23T12:08:21.000+02:00" CHECKSUM="95ae69d37f09b54116a7cae82ee459d5" CHECKSUMTYPE="MD5">
                    <ns3:FLocat LOCTYPE="OTHER" OTHERLOCTYPE="FILE" ns2:type="simple" ns2:href="page/IMG_4255.xml"/>
                </ns3:file>
                <ns3:file ID="PAGEXML_67" SEQ="67" MIMETYPE="application/xml" CREATED="2023-06-23T12:08:21.000+02:00" CHECKSUM="70181af5a72af698cb7c5b8ef4299d9f" CHECKSUMTYPE="MD5">
                    <ns3:FLocat LOCTYPE="OTHER" OTHERLOCTYPE="FILE" ns2:type="simple" ns2:href="page/IMG_4256.xml"/>
                </ns3:file>
                <ns3:file ID="PAGEXML_68" SEQ="68" MIMETYPE="application/xml" CREATED="2023-06-23T12:08:22.000+02:00" CHECKSUM="f9430a20a60bbe6978ef9463f5e3834d" CHECKSUMTYPE="MD5">
                    <ns3:FLocat LOCTYPE="OTHER" OTHERLOCTYPE="FILE" ns2:type="simple" ns2:href="page/IMG_4257.xml"/>
                </ns3:file>
                <ns3:file ID="PAGEXML_69" SEQ="69" MIMETYPE="application/xml" CREATED="2023-06-23T12:08:22.000+02:00" CHECKSUM="0f64aae3eecec33574354ec87f599eba" CHECKSUMTYPE="MD5">
                    <ns3:FLocat LOCTYPE="OTHER" OTHERLOCTYPE="FILE" ns2:type="simple" ns2:href="page/IMG_4258.xml"/>
                </ns3:file>
                <ns3:file ID="PAGEXML_70" SEQ="70" MIMETYPE="application/xml" CREATED="2023-06-23T12:08:22.000+02:00" CHECKSUM="fc1de98e4b7349580aeaad6aa3d9ad71" CHECKSUMTYPE="MD5">
                    <ns3:FLocat LOCTYPE="OTHER" OTHERLOCTYPE="FILE" ns2:type="simple" ns2:href="page/IMG_4259.xml"/>
                </ns3:file>
                <ns3:file ID="PAGEXML_71" SEQ="71" MIMETYPE="application/xml" CREATED="2023-06-23T12:08:22.000+02:00" CHECKSUM="90e1bf7bf4fdff2b3f51d5c5a238b868" CHECKSUMTYPE="MD5">
                    <ns3:FLocat LOCTYPE="OTHER" OTHERLOCTYPE="FILE" ns2:type="simple" ns2:href="page/IMG_4260.xml"/>
                </ns3:file>
                <ns3:file ID="PAGEXML_72" SEQ="72" MIMETYPE="application/xml" CREATED="2023-06-23T12:08:22.000+02:00" CHECKSUM="f1161dd54a208d66cf836813399ab5c8" CHECKSUMTYPE="MD5">
                    <ns3:FLocat LOCTYPE="OTHER" OTHERLOCTYPE="FILE" ns2:type="simple" ns2:href="page/IMG_4261.xml"/>
                </ns3:file>
                <ns3:file ID="PAGEXML_73" SEQ="73" MIMETYPE="application/xml" CREATED="2023-06-23T12:08:22.000+02:00" CHECKSUM="2099e7914983e29d65b98f489a98ccaf" CHECKSUMTYPE="MD5">
                    <ns3:FLocat LOCTYPE="OTHER" OTHERLOCTYPE="FILE" ns2:type="simple" ns2:href="page/IMG_4262.xml"/>
                </ns3:file>
                <ns3:file ID="PAGEXML_74" SEQ="74" MIMETYPE="application/xml" CREATED="2023-06-23T12:08:22.000+02:00" CHECKSUM="c82d63db7d0fe3781a6fb7fa9e4074e4" CHECKSUMTYPE="MD5">
                    <ns3:FLocat LOCTYPE="OTHER" OTHERLOCTYPE="FILE" ns2:type="simple" ns2:href="page/IMG_4263.xml"/>
                </ns3:file>
                <ns3:file ID="PAGEXML_75" SEQ="75" MIMETYPE="application/xml" CREATED="2023-06-23T12:08:22.000+02:00" CHECKSUM="bd691944cc5daeded68fe7952e8dbc81" CHECKSUMTYPE="MD5">
                    <ns3:FLocat LOCTYPE="OTHER" OTHERLOCTYPE="FILE" ns2:type="simple" ns2:href="page/IMG_4264.xml"/>
                </ns3:file>
                <ns3:file ID="PAGEXML_76" SEQ="76" MIMETYPE="application/xml" CREATED="2023-06-23T12:08:22.000+02:00" CHECKSUM="f428befda53e370e5af3bcfc084854ca" CHECKSUMTYPE="MD5">
                    <ns3:FLocat LOCTYPE="OTHER" OTHERLOCTYPE="FILE" ns2:type="simple" ns2:href="page/IMG_4265.xml"/>
                </ns3:file>
                <ns3:file ID="PAGEXML_77" SEQ="77" MIMETYPE="application/xml" CREATED="2023-06-23T12:08:23.000+02:00" CHECKSUM="08394e4fb68b5fbb63e44c1b95fc4a3a" CHECKSUMTYPE="MD5">
                    <ns3:FLocat LOCTYPE="OTHER" OTHERLOCTYPE="FILE" ns2:type="simple" ns2:href="page/IMG_4266.xml"/>
                </ns3:file>
                <ns3:file ID="PAGEXML_78" SEQ="78" MIMETYPE="application/xml" CREATED="2023-06-23T12:08:23.000+02:00" CHECKSUM="22248b9d69673651f692639834f90d53" CHECKSUMTYPE="MD5">
                    <ns3:FLocat LOCTYPE="OTHER" OTHERLOCTYPE="FILE" ns2:type="simple" ns2:href="page/IMG_4267.xml"/>
                </ns3:file>
                <ns3:file ID="PAGEXML_79" SEQ="79" MIMETYPE="application/xml" CREATED="2023-06-23T12:08:23.000+02:00" CHECKSUM="5eb1018be51fa46b81a30ec60f221008" CHECKSUMTYPE="MD5">
                    <ns3:FLocat LOCTYPE="OTHER" OTHERLOCTYPE="FILE" ns2:type="simple" ns2:href="page/IMG_4268.xml"/>
                </ns3:file>
                <ns3:file ID="PAGEXML_80" SEQ="80" MIMETYPE="application/xml" CREATED="2023-06-23T12:08:23.000+02:00" CHECKSUM="b27c4e5541d48530489ea9c02351dc32" CHECKSUMTYPE="MD5">
                    <ns3:FLocat LOCTYPE="OTHER" OTHERLOCTYPE="FILE" ns2:type="simple" ns2:href="page/IMG_4269.xml"/>
                </ns3:file>
                <ns3:file ID="PAGEXML_81" SEQ="81" MIMETYPE="application/xml" CREATED="2023-06-23T12:08:23.000+02:00" CHECKSUM="cbb7e9d193bae88317626e146de278ee" CHECKSUMTYPE="MD5">
                    <ns3:FLocat LOCTYPE="OTHER" OTHERLOCTYPE="FILE" ns2:type="simple" ns2:href="page/IMG_4270.xml"/>
                </ns3:file>
                <ns3:file ID="PAGEXML_82" SEQ="82" MIMETYPE="application/xml" CREATED="2023-06-23T12:08:23.000+02:00" CHECKSUM="49d0e4af3ab83043f7a175d867542d5a" CHECKSUMTYPE="MD5">
                    <ns3:FLocat LOCTYPE="OTHER" OTHERLOCTYPE="FILE" ns2:type="simple" ns2:href="page/IMG_4271.xml"/>
                </ns3:file>
                <ns3:file ID="PAGEXML_83" SEQ="83" MIMETYPE="application/xml" CREATED="2023-06-23T12:08:23.000+02:00" CHECKSUM="fa9f43e9729887fa6ce08c2ba3e8ef19" CHECKSUMTYPE="MD5">
                    <ns3:FLocat LOCTYPE="OTHER" OTHERLOCTYPE="FILE" ns2:type="simple" ns2:href="page/IMG_4272.xml"/>
                </ns3:file>
                <ns3:file ID="PAGEXML_84" SEQ="84" MIMETYPE="application/xml" CREATED="2023-06-23T12:08:23.000+02:00" CHECKSUM="4ded685ec63b3458dade793d7b9008dc" CHECKSUMTYPE="MD5">
                    <ns3:FLocat LOCTYPE="OTHER" OTHERLOCTYPE="FILE" ns2:type="simple" ns2:href="page/IMG_4273.xml"/>
                </ns3:file>
                <ns3:file ID="PAGEXML_85" SEQ="85" MIMETYPE="application/xml" CREATED="2023-06-23T12:08:24.000+02:00" CHECKSUM="2706420b8810d1d1a523208185a01af1" CHECKSUMTYPE="MD5">
                    <ns3:FLocat LOCTYPE="OTHER" OTHERLOCTYPE="FILE" ns2:type="simple" ns2:href="page/IMG_4274.xml"/>
                </ns3:file>
                <ns3:file ID="PAGEXML_86" SEQ="86" MIMETYPE="application/xml" CREATED="2023-06-23T12:08:24.000+02:00" CHECKSUM="714de8b2ddf541401f02259a8b5dfb3a" CHECKSUMTYPE="MD5">
                    <ns3:FLocat LOCTYPE="OTHER" OTHERLOCTYPE="FILE" ns2:type="simple" ns2:href="page/IMG_4275.xml"/>
                </ns3:file>
                <ns3:file ID="PAGEXML_87" SEQ="87" MIMETYPE="application/xml" CREATED="2023-06-23T12:08:24.000+02:00" CHECKSUM="0a775558c3ea0edfcea7af72b828cedb" CHECKSUMTYPE="MD5">
                    <ns3:FLocat LOCTYPE="OTHER" OTHERLOCTYPE="FILE" ns2:type="simple" ns2:href="page/IMG_4276.xml"/>
                </ns3:file>
                <ns3:file ID="PAGEXML_88" SEQ="88" MIMETYPE="application/xml" CREATED="2023-06-23T12:08:24.000+02:00" CHECKSUM="baee9af49bdaf41fc52c2a1a8666f3af" CHECKSUMTYPE="MD5">
                    <ns3:FLocat LOCTYPE="OTHER" OTHERLOCTYPE="FILE" ns2:type="simple" ns2:href="page/IMG_4277.xml"/>
                </ns3:file>
                <ns3:file ID="PAGEXML_89" SEQ="89" MIMETYPE="application/xml" CREATED="2023-06-23T12:08:24.000+02:00" CHECKSUM="5a92dbe1752185462e1973b7fc367bf2" CHECKSUMTYPE="MD5">
                    <ns3:FLocat LOCTYPE="OTHER" OTHERLOCTYPE="FILE" ns2:type="simple" ns2:href="page/IMG_4278.xml"/>
                </ns3:file>
                <ns3:file ID="PAGEXML_90" SEQ="90" MIMETYPE="application/xml" CREATED="2023-06-23T12:08:24.000+02:00" CHECKSUM="db138246a64a0528c5bee6046fccb546" CHECKSUMTYPE="MD5">
                    <ns3:FLocat LOCTYPE="OTHER" OTHERLOCTYPE="FILE" ns2:type="simple" ns2:href="page/IMG_4279.xml"/>
                </ns3:file>
                <ns3:file ID="PAGEXML_91" SEQ="91" MIMETYPE="application/xml" CREATED="2023-06-23T12:08:24.000+02:00" CHECKSUM="37efc1ec20596e87761e1732db81b47a" CHECKSUMTYPE="MD5">
                    <ns3:FLocat LOCTYPE="OTHER" OTHERLOCTYPE="FILE" ns2:type="simple" ns2:href="page/IMG_4280.xml"/>
                </ns3:file>
                <ns3:file ID="PAGEXML_92" SEQ="92" MIMETYPE="application/xml" CREATED="2023-06-23T12:08:24.000+02:00" CHECKSUM="a80e50da636b4ffec25e97f3a50bd7ba" CHECKSUMTYPE="MD5">
                    <ns3:FLocat LOCTYPE="OTHER" OTHERLOCTYPE="FILE" ns2:type="simple" ns2:href="page/IMG_4281.xml"/>
                </ns3:file>
                <ns3:file ID="PAGEXML_93" SEQ="93" MIMETYPE="application/xml" CREATED="2023-06-23T12:08:24.000+02:00" CHECKSUM="51d30871283ed746d3ee8be3b89ef13b" CHECKSUMTYPE="MD5">
                    <ns3:FLocat LOCTYPE="OTHER" OTHERLOCTYPE="FILE" ns2:type="simple" ns2:href="page/IMG_4282.xml"/>
                </ns3:file>
                <ns3:file ID="PAGEXML_94" SEQ="94" MIMETYPE="application/xml" CREATED="2023-06-23T12:08:25.000+02:00" CHECKSUM="7ae60e16d38c0ae2552e69632a5e08e6" CHECKSUMTYPE="MD5">
                    <ns3:FLocat LOCTYPE="OTHER" OTHERLOCTYPE="FILE" ns2:type="simple" ns2:href="page/IMG_4283.xml"/>
                </ns3:file>
                <ns3:file ID="PAGEXML_95" SEQ="95" MIMETYPE="application/xml" CREATED="2023-06-23T12:08:25.000+02:00" CHECKSUM="aaa5309216475a9d185d2dd3f4e9de01" CHECKSUMTYPE="MD5">
                    <ns3:FLocat LOCTYPE="OTHER" OTHERLOCTYPE="FILE" ns2:type="simple" ns2:href="page/IMG_4284.xml"/>
                </ns3:file>
                <ns3:file ID="PAGEXML_96" SEQ="96" MIMETYPE="application/xml" CREATED="2023-06-23T12:08:25.000+02:00" CHECKSUM="4965ef9ada454ad9c9db72ab77128fe2" CHECKSUMTYPE="MD5">
                    <ns3:FLocat LOCTYPE="OTHER" OTHERLOCTYPE="FILE" ns2:type="simple" ns2:href="page/IMG_4285.xml"/>
                </ns3:file>
                <ns3:file ID="PAGEXML_97" SEQ="97" MIMETYPE="application/xml" CREATED="2023-06-23T12:08:25.000+02:00" CHECKSUM="fb036a1495f21e3b360a154780110b97" CHECKSUMTYPE="MD5">
                    <ns3:FLocat LOCTYPE="OTHER" OTHERLOCTYPE="FILE" ns2:type="simple" ns2:href="page/IMG_4286.xml"/>
                </ns3:file>
                <ns3:file ID="PAGEXML_98" SEQ="98" MIMETYPE="application/xml" CREATED="2023-06-23T12:08:25.000+02:00" CHECKSUM="f04e93619feed15db2e0325652b63c51" CHECKSUMTYPE="MD5">
                    <ns3:FLocat LOCTYPE="OTHER" OTHERLOCTYPE="FILE" ns2:type="simple" ns2:href="page/IMG_4287.xml"/>
                </ns3:file>
                <ns3:file ID="PAGEXML_99" SEQ="99" MIMETYPE="application/xml" CREATED="2023-06-23T12:08:25.000+02:00" CHECKSUM="266f982ac5639b81d8f2f4bccd2252c8" CHECKSUMTYPE="MD5">
                    <ns3:FLocat LOCTYPE="OTHER" OTHERLOCTYPE="FILE" ns2:type="simple" ns2:href="page/IMG_4288.xml"/>
                </ns3:file>
                <ns3:file ID="PAGEXML_100" SEQ="100" MIMETYPE="application/xml" CREATED="2023-06-23T12:08:25.000+02:00" CHECKSUM="34459416547ebe1801e8b76c90e2d26c" CHECKSUMTYPE="MD5">
                    <ns3:FLocat LOCTYPE="OTHER" OTHERLOCTYPE="FILE" ns2:type="simple" ns2:href="page/IMG_4289.xml"/>
                </ns3:file>
                <ns3:file ID="PAGEXML_101" SEQ="101" MIMETYPE="application/xml" CREATED="2023-06-23T12:08:25.000+02:00" CHECKSUM="f3d3c10766a2e84ec790780678d79a6b" CHECKSUMTYPE="MD5">
                    <ns3:FLocat LOCTYPE="OTHER" OTHERLOCTYPE="FILE" ns2:type="simple" ns2:href="page/IMG_4290.xml"/>
                </ns3:file>
                <ns3:file ID="PAGEXML_102" SEQ="102" MIMETYPE="application/xml" CREATED="2023-06-23T12:08:26.000+02:00" CHECKSUM="f8fae71e7d6c9d977950e58a7be13a34" CHECKSUMTYPE="MD5">
                    <ns3:FLocat LOCTYPE="OTHER" OTHERLOCTYPE="FILE" ns2:type="simple" ns2:href="page/IMG_4291.xml"/>
                </ns3:file>
                <ns3:file ID="PAGEXML_103" SEQ="103" MIMETYPE="application/xml" CREATED="2023-06-23T12:08:26.000+02:00" CHECKSUM="ef1703fbd0f88e545c13fbdfbddba6e2" CHECKSUMTYPE="MD5">
                    <ns3:FLocat LOCTYPE="OTHER" OTHERLOCTYPE="FILE" ns2:type="simple" ns2:href="page/IMG_4292.xml"/>
                </ns3:file>
                <ns3:file ID="PAGEXML_104" SEQ="104" MIMETYPE="application/xml" CREATED="2023-06-23T12:08:26.000+02:00" CHECKSUM="986624dad8d763506c50201fd498a18f" CHECKSUMTYPE="MD5">
                    <ns3:FLocat LOCTYPE="OTHER" OTHERLOCTYPE="FILE" ns2:type="simple" ns2:href="page/IMG_4293.xml"/>
                </ns3:file>
                <ns3:file ID="PAGEXML_105" SEQ="105" MIMETYPE="application/xml" CREATED="2023-06-23T12:08:26.000+02:00" CHECKSUM="fae7c7b3f0ded55c7cd877028dae89df" CHECKSUMTYPE="MD5">
                    <ns3:FLocat LOCTYPE="OTHER" OTHERLOCTYPE="FILE" ns2:type="simple" ns2:href="page/IMG_4294.xml"/>
                </ns3:file>
                <ns3:file ID="PAGEXML_106" SEQ="106" MIMETYPE="application/xml" CREATED="2023-06-23T12:08:26.000+02:00" CHECKSUM="a52ed8004a77043c1873c4cd3d56ce06" CHECKSUMTYPE="MD5">
                    <ns3:FLocat LOCTYPE="OTHER" OTHERLOCTYPE="FILE" ns2:type="simple" ns2:href="page/IMG_4295.xml"/>
                </ns3:file>
            </ns3:fileGrp>
        </ns3:fileGrp>
    </ns3:fileSec>
    <ns3:structMap ID="TRP_STRUCTMAP" TYPE="MANUSCRIPT">
        <ns3:div ID="TRP_DOC_DIV" ADMID="MD_ORIG">
            <ns3:div ID="PAGE_1" ORDER="1" TYPE="SINGLE_PAGE">
                <ns3:fptr>
                    <ns3:area FILEID="PAGEXML_1"/>
                </ns3:fptr>
            </ns3:div>
            <ns3:div ID="PAGE_2" ORDER="2" TYPE="SINGLE_PAGE">
                <ns3:fptr>
                    <ns3:area FILEID="PAGEXML_2"/>
                </ns3:fptr>
            </ns3:div>
            <ns3:div ID="PAGE_3" ORDER="3" TYPE="SINGLE_PAGE">
                <ns3:fptr>
                    <ns3:area FILEID="PAGEXML_3"/>
                </ns3:fptr>
            </ns3:div>
            <ns3:div ID="PAGE_4" ORDER="4" TYPE="SINGLE_PAGE">
                <ns3:fptr>
                    <ns3:area FILEID="PAGEXML_4"/>
                </ns3:fptr>
            </ns3:div>
            <ns3:div ID="PAGE_5" ORDER="5" TYPE="SINGLE_PAGE">
                <ns3:fptr>
                    <ns3:area FILEID="PAGEXML_5"/>
                </ns3:fptr>
            </ns3:div>
            <ns3:div ID="PAGE_6" ORDER="6" TYPE="SINGLE_PAGE">
                <ns3:fptr>
                    <ns3:area FILEID="PAGEXML_6"/>
                </ns3:fptr>
            </ns3:div>
            <ns3:div ID="PAGE_7" ORDER="7" TYPE="SINGLE_PAGE">
                <ns3:fptr>
                    <ns3:area FILEID="PAGEXML_7"/>
                </ns3:fptr>
            </ns3:div>
            <ns3:div ID="PAGE_8" ORDER="8" TYPE="SINGLE_PAGE">
                <ns3:fptr>
                    <ns3:area FILEID="PAGEXML_8"/>
                </ns3:fptr>
            </ns3:div>
            <ns3:div ID="PAGE_9" ORDER="9" TYPE="SINGLE_PAGE">
                <ns3:fptr>
                    <ns3:area FILEID="PAGEXML_9"/>
                </ns3:fptr>
            </ns3:div>
            <ns3:div ID="PAGE_10" ORDER="10" TYPE="SINGLE_PAGE">
                <ns3:fptr>
                    <ns3:area FILEID="PAGEXML_10"/>
                </ns3:fptr>
            </ns3:div>
            <ns3:div ID="PAGE_11" ORDER="11" TYPE="SINGLE_PAGE">
                <ns3:fptr>
                    <ns3:area FILEID="PAGEXML_11"/>
                </ns3:fptr>
            </ns3:div>
            <ns3:div ID="PAGE_12" ORDER="12" TYPE="SINGLE_PAGE">
                <ns3:fptr>
                    <ns3:area FILEID="PAGEXML_12"/>
                </ns3:fptr>
            </ns3:div>
            <ns3:div ID="PAGE_13" ORDER="13" TYPE="SINGLE_PAGE">
                <ns3:fptr>
                    <ns3:area FILEID="PAGEXML_13"/>
                </ns3:fptr>
            </ns3:div>
            <ns3:div ID="PAGE_14" ORDER="14" TYPE="SINGLE_PAGE">
                <ns3:fptr>
                    <ns3:area FILEID="PAGEXML_14"/>
                </ns3:fptr>
            </ns3:div>
            <ns3:div ID="PAGE_15" ORDER="15" TYPE="SINGLE_PAGE">
                <ns3:fptr>
                    <ns3:area FILEID="PAGEXML_15"/>
                </ns3:fptr>
            </ns3:div>
            <ns3:div ID="PAGE_16" ORDER="16" TYPE="SINGLE_PAGE">
                <ns3:fptr>
                    <ns3:area FILEID="PAGEXML_16"/>
                </ns3:fptr>
            </ns3:div>
            <ns3:div ID="PAGE_17" ORDER="17" TYPE="SINGLE_PAGE">
                <ns3:fptr>
                    <ns3:area FILEID="PAGEXML_17"/>
                </ns3:fptr>
            </ns3:div>
            <ns3:div ID="PAGE_18" ORDER="18" TYPE="SINGLE_PAGE">
                <ns3:fptr>
                    <ns3:area FILEID="PAGEXML_18"/>
                </ns3:fptr>
            </ns3:div>
            <ns3:div ID="PAGE_19" ORDER="19" TYPE="SINGLE_PAGE">
                <ns3:fptr>
                    <ns3:area FILEID="PAGEXML_19"/>
                </ns3:fptr>
            </ns3:div>
            <ns3:div ID="PAGE_20" ORDER="20" TYPE="SINGLE_PAGE">
                <ns3:fptr>
                    <ns3:area FILEID="PAGEXML_20"/>
                </ns3:fptr>
            </ns3:div>
            <ns3:div ID="PAGE_21" ORDER="21" TYPE="SINGLE_PAGE">
                <ns3:fptr>
                    <ns3:area FILEID="PAGEXML_21"/>
                </ns3:fptr>
            </ns3:div>
            <ns3:div ID="PAGE_22" ORDER="22" TYPE="SINGLE_PAGE">
                <ns3:fptr>
                    <ns3:area FILEID="PAGEXML_22"/>
                </ns3:fptr>
            </ns3:div>
            <ns3:div ID="PAGE_23" ORDER="23" TYPE="SINGLE_PAGE">
                <ns3:fptr>
                    <ns3:area FILEID="PAGEXML_23"/>
                </ns3:fptr>
            </ns3:div>
            <ns3:div ID="PAGE_24" ORDER="24" TYPE="SINGLE_PAGE">
                <ns3:fptr>
                    <ns3:area FILEID="PAGEXML_24"/>
                </ns3:fptr>
            </ns3:div>
            <ns3:div ID="PAGE_25" ORDER="25" TYPE="SINGLE_PAGE">
                <ns3:fptr>
                    <ns3:area FILEID="PAGEXML_25"/>
                </ns3:fptr>
            </ns3:div>
            <ns3:div ID="PAGE_26" ORDER="26" TYPE="SINGLE_PAGE">
                <ns3:fptr>
                    <ns3:area FILEID="PAGEXML_26"/>
                </ns3:fptr>
            </ns3:div>
            <ns3:div ID="PAGE_27" ORDER="27" TYPE="SINGLE_PAGE">
                <ns3:fptr>
                    <ns3:area FILEID="PAGEXML_27"/>
                </ns3:fptr>
            </ns3:div>
            <ns3:div ID="PAGE_28" ORDER="28" TYPE="SINGLE_PAGE">
                <ns3:fptr>
                    <ns3:area FILEID="PAGEXML_28"/>
                </ns3:fptr>
            </ns3:div>
            <ns3:div ID="PAGE_29" ORDER="29" TYPE="SINGLE_PAGE">
                <ns3:fptr>
                    <ns3:area FILEID="PAGEXML_29"/>
                </ns3:fptr>
            </ns3:div>
            <ns3:div ID="PAGE_30" ORDER="30" TYPE="SINGLE_PAGE">
                <ns3:fptr>
                    <ns3:area FILEID="PAGEXML_30"/>
                </ns3:fptr>
            </ns3:div>
            <ns3:div ID="PAGE_31" ORDER="31" TYPE="SINGLE_PAGE">
                <ns3:fptr>
                    <ns3:area FILEID="PAGEXML_31"/>
                </ns3:fptr>
            </ns3:div>
            <ns3:div ID="PAGE_32" ORDER="32" TYPE="SINGLE_PAGE">
                <ns3:fptr>
                    <ns3:area FILEID="PAGEXML_32"/>
                </ns3:fptr>
            </ns3:div>
            <ns3:div ID="PAGE_33" ORDER="33" TYPE="SINGLE_PAGE">
                <ns3:fptr>
                    <ns3:area FILEID="PAGEXML_33"/>
                </ns3:fptr>
            </ns3:div>
            <ns3:div ID="PAGE_34" ORDER="34" TYPE="SINGLE_PAGE">
                <ns3:fptr>
                    <ns3:area FILEID="PAGEXML_34"/>
                </ns3:fptr>
            </ns3:div>
            <ns3:div ID="PAGE_35" ORDER="35" TYPE="SINGLE_PAGE">
                <ns3:fptr>
                    <ns3:area FILEID="PAGEXML_35"/>
                </ns3:fptr>
            </ns3:div>
            <ns3:div ID="PAGE_36" ORDER="36" TYPE="SINGLE_PAGE">
                <ns3:fptr>
                    <ns3:area FILEID="PAGEXML_36"/>
                </ns3:fptr>
            </ns3:div>
            <ns3:div ID="PAGE_37" ORDER="37" TYPE="SINGLE_PAGE">
                <ns3:fptr>
                    <ns3:area FILEID="PAGEXML_37"/>
                </ns3:fptr>
            </ns3:div>
            <ns3:div ID="PAGE_38" ORDER="38" TYPE="SINGLE_PAGE">
                <ns3:fptr>
                    <ns3:area FILEID="PAGEXML_38"/>
                </ns3:fptr>
            </ns3:div>
            <ns3:div ID="PAGE_39" ORDER="39" TYPE="SINGLE_PAGE">
                <ns3:fptr>
                    <ns3:area FILEID="PAGEXML_39"/>
                </ns3:fptr>
            </ns3:div>
            <ns3:div ID="PAGE_40" ORDER="40" TYPE="SINGLE_PAGE">
                <ns3:fptr>
                    <ns3:area FILEID="PAGEXML_40"/>
                </ns3:fptr>
            </ns3:div>
            <ns3:div ID="PAGE_41" ORDER="41" TYPE="SINGLE_PAGE">
                <ns3:fptr>
                    <ns3:area FILEID="PAGEXML_41"/>
                </ns3:fptr>
            </ns3:div>
            <ns3:div ID="PAGE_42" ORDER="42" TYPE="SINGLE_PAGE">
                <ns3:fptr>
                    <ns3:area FILEID="PAGEXML_42"/>
                </ns3:fptr>
            </ns3:div>
            <ns3:div ID="PAGE_43" ORDER="43" TYPE="SINGLE_PAGE">
                <ns3:fptr>
                    <ns3:area FILEID="PAGEXML_43"/>
                </ns3:fptr>
            </ns3:div>
            <ns3:div ID="PAGE_44" ORDER="44" TYPE="SINGLE_PAGE">
                <ns3:fptr>
                    <ns3:area FILEID="PAGEXML_44"/>
                </ns3:fptr>
            </ns3:div>
            <ns3:div ID="PAGE_45" ORDER="45" TYPE="SINGLE_PAGE">
                <ns3:fptr>
                    <ns3:area FILEID="PAGEXML_45"/>
                </ns3:fptr>
            </ns3:div>
            <ns3:div ID="PAGE_46" ORDER="46" TYPE="SINGLE_PAGE">
                <ns3:fptr>
                    <ns3:area FILEID="PAGEXML_46"/>
                </ns3:fptr>
            </ns3:div>
            <ns3:div ID="PAGE_47" ORDER="47" TYPE="SINGLE_PAGE">
                <ns3:fptr>
                    <ns3:area FILEID="PAGEXML_47"/>
                </ns3:fptr>
            </ns3:div>
            <ns3:div ID="PAGE_48" ORDER="48" TYPE="SINGLE_PAGE">
                <ns3:fptr>
                    <ns3:area FILEID="PAGEXML_48"/>
                </ns3:fptr>
            </ns3:div>
            <ns3:div ID="PAGE_49" ORDER="49" TYPE="SINGLE_PAGE">
                <ns3:fptr>
                    <ns3:area FILEID="PAGEXML_49"/>
                </ns3:fptr>
            </ns3:div>
            <ns3:div ID="PAGE_50" ORDER="50" TYPE="SINGLE_PAGE">
                <ns3:fptr>
                    <ns3:area FILEID="PAGEXML_50"/>
                </ns3:fptr>
            </ns3:div>
            <ns3:div ID="PAGE_51" ORDER="51" TYPE="SINGLE_PAGE">
                <ns3:fptr>
                    <ns3:area FILEID="PAGEXML_51"/>
                </ns3:fptr>
            </ns3:div>
            <ns3:div ID="PAGE_52" ORDER="52" TYPE="SINGLE_PAGE">
                <ns3:fptr>
                    <ns3:area FILEID="PAGEXML_52"/>
                </ns3:fptr>
            </ns3:div>
            <ns3:div ID="PAGE_53" ORDER="53" TYPE="SINGLE_PAGE">
                <ns3:fptr>
                    <ns3:area FILEID="PAGEXML_53"/>
                </ns3:fptr>
            </ns3:div>
            <ns3:div ID="PAGE_54" ORDER="54" TYPE="SINGLE_PAGE">
                <ns3:fptr>
                    <ns3:area FILEID="PAGEXML_54"/>
                </ns3:fptr>
            </ns3:div>
            <ns3:div ID="PAGE_55" ORDER="55" TYPE="SINGLE_PAGE">
                <ns3:fptr>
                    <ns3:area FILEID="PAGEXML_55"/>
                </ns3:fptr>
            </ns3:div>
            <ns3:div ID="PAGE_56" ORDER="56" TYPE="SINGLE_PAGE">
                <ns3:fptr>
                    <ns3:area FILEID="PAGEXML_56"/>
                </ns3:fptr>
            </ns3:div>
            <ns3:div ID="PAGE_57" ORDER="57" TYPE="SINGLE_PAGE">
                <ns3:fptr>
                    <ns3:area FILEID="PAGEXML_57"/>
                </ns3:fptr>
            </ns3:div>
            <ns3:div ID="PAGE_58" ORDER="58" TYPE="SINGLE_PAGE">
                <ns3:fptr>
                    <ns3:area FILEID="PAGEXML_58"/>
                </ns3:fptr>
            </ns3:div>
            <ns3:div ID="PAGE_59" ORDER="59" TYPE="SINGLE_PAGE">
                <ns3:fptr>
                    <ns3:area FILEID="PAGEXML_59"/>
                </ns3:fptr>
            </ns3:div>
            <ns3:div ID="PAGE_60" ORDER="60" TYPE="SINGLE_PAGE">
                <ns3:fptr>
                    <ns3:area FILEID="PAGEXML_60"/>
                </ns3:fptr>
            </ns3:div>
            <ns3:div ID="PAGE_61" ORDER="61" TYPE="SINGLE_PAGE">
                <ns3:fptr>
                    <ns3:area FILEID="PAGEXML_61"/>
                </ns3:fptr>
            </ns3:div>
            <ns3:div ID="PAGE_62" ORDER="62" TYPE="SINGLE_PAGE">
                <ns3:fptr>
                    <ns3:area FILEID="PAGEXML_62"/>
                </ns3:fptr>
            </ns3:div>
            <ns3:div ID="PAGE_63" ORDER="63" TYPE="SINGLE_PAGE">
                <ns3:fptr>
                    <ns3:area FILEID="PAGEXML_63"/>
                </ns3:fptr>
            </ns3:div>
            <ns3:div ID="PAGE_64" ORDER="64" TYPE="SINGLE_PAGE">
                <ns3:fptr>
                    <ns3:area FILEID="PAGEXML_64"/>
                </ns3:fptr>
            </ns3:div>
            <ns3:div ID="PAGE_65" ORDER="65" TYPE="SINGLE_PAGE">
                <ns3:fptr>
                    <ns3:area FILEID="PAGEXML_65"/>
                </ns3:fptr>
            </ns3:div>
            <ns3:div ID="PAGE_66" ORDER="66" TYPE="SINGLE_PAGE">
                <ns3:fptr>
                    <ns3:area FILEID="PAGEXML_66"/>
                </ns3:fptr>
            </ns3:div>
            <ns3:div ID="PAGE_67" ORDER="67" TYPE="SINGLE_PAGE">
                <ns3:fptr>
                    <ns3:area FILEID="PAGEXML_67"/>
                </ns3:fptr>
            </ns3:div>
            <ns3:div ID="PAGE_68" ORDER="68" TYPE="SINGLE_PAGE">
                <ns3:fptr>
                    <ns3:area FILEID="PAGEXML_68"/>
                </ns3:fptr>
            </ns3:div>
            <ns3:div ID="PAGE_69" ORDER="69" TYPE="SINGLE_PAGE">
                <ns3:fptr>
                    <ns3:area FILEID="PAGEXML_69"/>
                </ns3:fptr>
            </ns3:div>
            <ns3:div ID="PAGE_70" ORDER="70" TYPE="SINGLE_PAGE">
                <ns3:fptr>
                    <ns3:area FILEID="PAGEXML_70"/>
                </ns3:fptr>
            </ns3:div>
            <ns3:div ID="PAGE_71" ORDER="71" TYPE="SINGLE_PAGE">
                <ns3:fptr>
                    <ns3:area FILEID="PAGEXML_71"/>
                </ns3:fptr>
            </ns3:div>
            <ns3:div ID="PAGE_72" ORDER="72" TYPE="SINGLE_PAGE">
                <ns3:fptr>
                    <ns3:area FILEID="PAGEXML_72"/>
                </ns3:fptr>
            </ns3:div>
            <ns3:div ID="PAGE_73" ORDER="73" TYPE="SINGLE_PAGE">
                <ns3:fptr>
                    <ns3:area FILEID="PAGEXML_73"/>
                </ns3:fptr>
            </ns3:div>
            <ns3:div ID="PAGE_74" ORDER="74" TYPE="SINGLE_PAGE">
                <ns3:fptr>
                    <ns3:area FILEID="PAGEXML_74"/>
                </ns3:fptr>
            </ns3:div>
            <ns3:div ID="PAGE_75" ORDER="75" TYPE="SINGLE_PAGE">
                <ns3:fptr>
                    <ns3:area FILEID="PAGEXML_75"/>
                </ns3:fptr>
            </ns3:div>
            <ns3:div ID="PAGE_76" ORDER="76" TYPE="SINGLE_PAGE">
                <ns3:fptr>
                    <ns3:area FILEID="PAGEXML_76"/>
                </ns3:fptr>
            </ns3:div>
            <ns3:div ID="PAGE_77" ORDER="77" TYPE="SINGLE_PAGE">
                <ns3:fptr>
                    <ns3:area FILEID="PAGEXML_77"/>
                </ns3:fptr>
            </ns3:div>
            <ns3:div ID="PAGE_78" ORDER="78" TYPE="SINGLE_PAGE">
                <ns3:fptr>
                    <ns3:area FILEID="PAGEXML_78"/>
                </ns3:fptr>
            </ns3:div>
            <ns3:div ID="PAGE_79" ORDER="79" TYPE="SINGLE_PAGE">
                <ns3:fptr>
                    <ns3:area FILEID="PAGEXML_79"/>
                </ns3:fptr>
            </ns3:div>
            <ns3:div ID="PAGE_80" ORDER="80" TYPE="SINGLE_PAGE">
                <ns3:fptr>
                    <ns3:area FILEID="PAGEXML_80"/>
                </ns3:fptr>
            </ns3:div>
            <ns3:div ID="PAGE_81" ORDER="81" TYPE="SINGLE_PAGE">
                <ns3:fptr>
                    <ns3:area FILEID="PAGEXML_81"/>
                </ns3:fptr>
            </ns3:div>
            <ns3:div ID="PAGE_82" ORDER="82" TYPE="SINGLE_PAGE">
                <ns3:fptr>
                    <ns3:area FILEID="PAGEXML_82"/>
                </ns3:fptr>
            </ns3:div>
            <ns3:div ID="PAGE_83" ORDER="83" TYPE="SINGLE_PAGE">
                <ns3:fptr>
                    <ns3:area FILEID="PAGEXML_83"/>
                </ns3:fptr>
            </ns3:div>
            <ns3:div ID="PAGE_84" ORDER="84" TYPE="SINGLE_PAGE">
                <ns3:fptr>
                    <ns3:area FILEID="PAGEXML_84"/>
                </ns3:fptr>
            </ns3:div>
            <ns3:div ID="PAGE_85" ORDER="85" TYPE="SINGLE_PAGE">
                <ns3:fptr>
                    <ns3:area FILEID="PAGEXML_85"/>
                </ns3:fptr>
            </ns3:div>
            <ns3:div ID="PAGE_86" ORDER="86" TYPE="SINGLE_PAGE">
                <ns3:fptr>
                    <ns3:area FILEID="PAGEXML_86"/>
                </ns3:fptr>
            </ns3:div>
            <ns3:div ID="PAGE_87" ORDER="87" TYPE="SINGLE_PAGE">
                <ns3:fptr>
                    <ns3:area FILEID="PAGEXML_87"/>
                </ns3:fptr>
            </ns3:div>
            <ns3:div ID="PAGE_88" ORDER="88" TYPE="SINGLE_PAGE">
                <ns3:fptr>
                    <ns3:area FILEID="PAGEXML_88"/>
                </ns3:fptr>
            </ns3:div>
            <ns3:div ID="PAGE_89" ORDER="89" TYPE="SINGLE_PAGE">
                <ns3:fptr>
                    <ns3:area FILEID="PAGEXML_89"/>
                </ns3:fptr>
            </ns3:div>
            <ns3:div ID="PAGE_90" ORDER="90" TYPE="SINGLE_PAGE">
                <ns3:fptr>
                    <ns3:area FILEID="PAGEXML_90"/>
                </ns3:fptr>
            </ns3:div>
            <ns3:div ID="PAGE_91" ORDER="91" TYPE="SINGLE_PAGE">
                <ns3:fptr>
                    <ns3:area FILEID="PAGEXML_91"/>
                </ns3:fptr>
            </ns3:div>
            <ns3:div ID="PAGE_92" ORDER="92" TYPE="SINGLE_PAGE">
                <ns3:fptr>
                    <ns3:area FILEID="PAGEXML_92"/>
                </ns3:fptr>
            </ns3:div>
            <ns3:div ID="PAGE_93" ORDER="93" TYPE="SINGLE_PAGE">
                <ns3:fptr>
                    <ns3:area FILEID="PAGEXML_93"/>
                </ns3:fptr>
            </ns3:div>
            <ns3:div ID="PAGE_94" ORDER="94" TYPE="SINGLE_PAGE">
                <ns3:fptr>
                    <ns3:area FILEID="PAGEXML_94"/>
                </ns3:fptr>
            </ns3:div>
            <ns3:div ID="PAGE_95" ORDER="95" TYPE="SINGLE_PAGE">
                <ns3:fptr>
                    <ns3:area FILEID="PAGEXML_95"/>
                </ns3:fptr>
            </ns3:div>
            <ns3:div ID="PAGE_96" ORDER="96" TYPE="SINGLE_PAGE">
                <ns3:fptr>
                    <ns3:area FILEID="PAGEXML_96"/>
                </ns3:fptr>
            </ns3:div>
            <ns3:div ID="PAGE_97" ORDER="97" TYPE="SINGLE_PAGE">
                <ns3:fptr>
                    <ns3:area FILEID="PAGEXML_97"/>
                </ns3:fptr>
            </ns3:div>
            <ns3:div ID="PAGE_98" ORDER="98" TYPE="SINGLE_PAGE">
                <ns3:fptr>
                    <ns3:area FILEID="PAGEXML_98"/>
                </ns3:fptr>
            </ns3:div>
            <ns3:div ID="PAGE_99" ORDER="99" TYPE="SINGLE_PAGE">
                <ns3:fptr>
                    <ns3:area FILEID="PAGEXML_99"/>
                </ns3:fptr>
            </ns3:div>
            <ns3:div ID="PAGE_100" ORDER="100" TYPE="SINGLE_PAGE">
                <ns3:fptr>
                    <ns3:area FILEID="PAGEXML_100"/>
                </ns3:fptr>
            </ns3:div>
            <ns3:div ID="PAGE_101" ORDER="101" TYPE="SINGLE_PAGE">
                <ns3:fptr>
                    <ns3:area FILEID="PAGEXML_101"/>
                </ns3:fptr>
            </ns3:div>
            <ns3:div ID="PAGE_102" ORDER="102" TYPE="SINGLE_PAGE">
                <ns3:fptr>
                    <ns3:area FILEID="PAGEXML_102"/>
                </ns3:fptr>
            </ns3:div>
            <ns3:div ID="PAGE_103" ORDER="103" TYPE="SINGLE_PAGE">
                <ns3:fptr>
                    <ns3:area FILEID="PAGEXML_103"/>
                </ns3:fptr>
            </ns3:div>
            <ns3:div ID="PAGE_104" ORDER="104" TYPE="SINGLE_PAGE">
                <ns3:fptr>
                    <ns3:area FILEID="PAGEXML_104"/>
                </ns3:fptr>
            </ns3:div>
            <ns3:div ID="PAGE_105" ORDER="105" TYPE="SINGLE_PAGE">
                <ns3:fptr>
                    <ns3:area FILEID="PAGEXML_105"/>
                </ns3:fptr>
            </ns3:div>
            <ns3:div ID="PAGE_106" ORDER="106" TYPE="SINGLE_PAGE">
                <ns3:fptr>
                    <ns3:area FILEID="PAGEXML_106"/>
                </ns3:fptr>
            </ns3:div>
        </ns3:div>
    </ns3:structMap>
</ns3:mets>
