<?xml version="1.0" encoding="UTF-8" standalone="yes"?>
<ns3:mets xmlns:ns2="http://www.w3.org/1999/xlink" xmlns:ns3="http://www.loc.gov/METS/" xmlns:xsi="http://www.w3.org/2001/XMLSchema-instance" OBJID="1334833" LABEL="B IX 478_duplicated" PROFILE="TRP_V1" xsi:schemaLocation="http://www.loc.gov/METS/ http://www.loc.gov/standards/mets/mets.xsd">
    <ns3:metsHdr CREATEDATE="2023-06-23T11:48:36.693+02:00" LASTMODDATE="2023-06-23T11:48:36.693+02:00" RECORDSTATUS="SUBMITTED">
        <ns3:agent ROLE="CREATOR" TYPE="ORGANIZATION">
            <ns3:name>UIBK</ns3:name>
            <ns3:note>This METS file was generated by Transkribus</ns3:note>
        </ns3:agent>
    </ns3:metsHdr>
    <ns3:amdSec ID="SOURCE">
        <ns3:sourceMD ID="MD_ORIG">
            <ns3:mdWrap ID="TRP_DOC_MD" MDTYPE="OTHER">
                <ns3:xmlData>
                    <trpDocMetadata>
                        <docId>1334833</docId>
                        <title>B IX 478_duplicated</title>
                        <uploadTimestamp>1676391459156</uploadTimestamp>
                        <uploader>myrjam.hostettler@students.unibe.ch</uploader>
                        <uploaderId>68497</uploaderId>
                        <nrOfPages>99</nrOfPages>
                        <pageId>52361045</pageId>
                        <url>https://files.transkribus.eu/Get?fileType=view&amp;id=FKTZQWRWZIAEEODYUKSUHVNQ</url>
                        <thumbUrl>https://files.transkribus.eu/Get?fileType=thumb&amp;id=FKTZQWRWZIAEEODYUKSUHVNQ</thumbUrl>
                        <externalId>NA</externalId>
                        <authority>NA</authority>
                        <status>0</status>
                        <fimgStoreColl>TrpDoc_DEA_505031</fimgStoreColl>
                        <localFolder>/mnt/transkribus/export/TRP_EXPORT_3166530333095738059/1334833/B_IX_478_duplicated</localFolder>
                        <origDocId>607247</origDocId>
                        <collectionList>
                            <colList>
<colId>187323</colId>
<colName>StABE_Turmbücher_DH_flow</colName>
<description>created by myrjam.hostettler@students.unibe.ch</description>
<crowdsourcing>false</crowdsourcing>
<elearning>false</elearning>
<nrOfDocuments>0</nrOfDocuments>
                            </colList>
                        </collectionList>
                    </trpDocMetadata>
                </ns3:xmlData>
            </ns3:mdWrap>
        </ns3:sourceMD>
    </ns3:amdSec>
    <ns3:fileSec>
        <ns3:fileGrp ID="MASTER">
            <ns3:fileGrp ID="PAGEXML">
                <ns3:file ID="PAGEXML_1" SEQ="1" MIMETYPE="application/xml" CREATED="2023-06-23T11:48:27.000+02:00" CHECKSUM="adcfbce792e36b8f6e3b35fd39ea4975" CHECKSUMTYPE="MD5">
                    <ns3:FLocat LOCTYPE="OTHER" OTHERLOCTYPE="FILE" ns2:type="simple" ns2:href="page/Turmbuch_StAB B IX 478_00001-20200925_091517.xml"/>
                </ns3:file>
                <ns3:file ID="PAGEXML_2" SEQ="2" MIMETYPE="application/xml" CREATED="2023-06-23T11:48:27.000+02:00" CHECKSUM="68fb7f75abbf5ccf9ee9e3b8d0bb92cc" CHECKSUMTYPE="MD5">
                    <ns3:FLocat LOCTYPE="OTHER" OTHERLOCTYPE="FILE" ns2:type="simple" ns2:href="page/Turmbuch_StAB B IX 478_00002-20200925_091530.xml"/>
                </ns3:file>
                <ns3:file ID="PAGEXML_3" SEQ="3" MIMETYPE="application/xml" CREATED="2023-06-23T11:48:27.000+02:00" CHECKSUM="83c229372ee175681f6eacf8120b3ca5" CHECKSUMTYPE="MD5">
                    <ns3:FLocat LOCTYPE="OTHER" OTHERLOCTYPE="FILE" ns2:type="simple" ns2:href="page/Turmbuch_StAB B IX 478_00003-20200925_091535.xml"/>
                </ns3:file>
                <ns3:file ID="PAGEXML_4" SEQ="4" MIMETYPE="application/xml" CREATED="2023-06-23T11:48:27.000+02:00" CHECKSUM="a22454fbce09e73a74e5921f304c8f4f" CHECKSUMTYPE="MD5">
                    <ns3:FLocat LOCTYPE="OTHER" OTHERLOCTYPE="FILE" ns2:type="simple" ns2:href="page/Turmbuch_StAB B IX 478_00004-20200925_091540.xml"/>
                </ns3:file>
                <ns3:file ID="PAGEXML_5" SEQ="5" MIMETYPE="application/xml" CREATED="2023-06-23T11:48:27.000+02:00" CHECKSUM="4cfa94d1767533a1113ae2fdf005f621" CHECKSUMTYPE="MD5">
                    <ns3:FLocat LOCTYPE="OTHER" OTHERLOCTYPE="FILE" ns2:type="simple" ns2:href="page/Turmbuch_StAB B IX 478_00005-20200925_091545.xml"/>
                </ns3:file>
                <ns3:file ID="PAGEXML_6" SEQ="6" MIMETYPE="application/xml" CREATED="2023-06-23T11:48:27.000+02:00" CHECKSUM="50004f83561f73a861cb90be0439ab20" CHECKSUMTYPE="MD5">
                    <ns3:FLocat LOCTYPE="OTHER" OTHERLOCTYPE="FILE" ns2:type="simple" ns2:href="page/Turmbuch_StAB B IX 478_00006-20200925_091554.xml"/>
                </ns3:file>
                <ns3:file ID="PAGEXML_7" SEQ="7" MIMETYPE="application/xml" CREATED="2023-06-23T11:48:27.000+02:00" CHECKSUM="4a8e77f0f93cbd82151217a2da361aa1" CHECKSUMTYPE="MD5">
                    <ns3:FLocat LOCTYPE="OTHER" OTHERLOCTYPE="FILE" ns2:type="simple" ns2:href="page/Turmbuch_StAB B IX 478_00007-20200925_091559.xml"/>
                </ns3:file>
                <ns3:file ID="PAGEXML_8" SEQ="8" MIMETYPE="application/xml" CREATED="2023-06-23T11:48:28.000+02:00" CHECKSUM="0b424643d193cc1901f1fadd6cf362e9" CHECKSUMTYPE="MD5">
                    <ns3:FLocat LOCTYPE="OTHER" OTHERLOCTYPE="FILE" ns2:type="simple" ns2:href="page/Turmbuch_StAB B IX 478_00008-20200925_091606.xml"/>
                </ns3:file>
                <ns3:file ID="PAGEXML_9" SEQ="9" MIMETYPE="application/xml" CREATED="2023-06-23T11:48:28.000+02:00" CHECKSUM="986c9951365c5af63d142f4dc6cd81f8" CHECKSUMTYPE="MD5">
                    <ns3:FLocat LOCTYPE="OTHER" OTHERLOCTYPE="FILE" ns2:type="simple" ns2:href="page/Turmbuch_StAB B IX 478_00009-20200925_091614.xml"/>
                </ns3:file>
                <ns3:file ID="PAGEXML_10" SEQ="10" MIMETYPE="application/xml" CREATED="2023-06-23T11:48:28.000+02:00" CHECKSUM="3d6b12f97424126b576cf2f9cd67348a" CHECKSUMTYPE="MD5">
                    <ns3:FLocat LOCTYPE="OTHER" OTHERLOCTYPE="FILE" ns2:type="simple" ns2:href="page/Turmbuch_StAB B IX 478_00010-20200925_091631.xml"/>
                </ns3:file>
                <ns3:file ID="PAGEXML_11" SEQ="11" MIMETYPE="application/xml" CREATED="2023-06-23T11:48:28.000+02:00" CHECKSUM="9355192525077729c38b686893f1f204" CHECKSUMTYPE="MD5">
                    <ns3:FLocat LOCTYPE="OTHER" OTHERLOCTYPE="FILE" ns2:type="simple" ns2:href="page/Turmbuch_StAB B IX 478_00011-20200925_091645.xml"/>
                </ns3:file>
                <ns3:file ID="PAGEXML_12" SEQ="12" MIMETYPE="application/xml" CREATED="2023-06-23T11:48:28.000+02:00" CHECKSUM="d363a5e7959edddc9a563b4147041aa3" CHECKSUMTYPE="MD5">
                    <ns3:FLocat LOCTYPE="OTHER" OTHERLOCTYPE="FILE" ns2:type="simple" ns2:href="page/Turmbuch_StAB B IX 478_00012-20200925_091650.xml"/>
                </ns3:file>
                <ns3:file ID="PAGEXML_13" SEQ="13" MIMETYPE="application/xml" CREATED="2023-06-23T11:48:28.000+02:00" CHECKSUM="cce5ee4d015af87a9ec54f76253d54a1" CHECKSUMTYPE="MD5">
                    <ns3:FLocat LOCTYPE="OTHER" OTHERLOCTYPE="FILE" ns2:type="simple" ns2:href="page/Turmbuch_StAB B IX 478_00013-20200925_091656.xml"/>
                </ns3:file>
                <ns3:file ID="PAGEXML_14" SEQ="14" MIMETYPE="application/xml" CREATED="2023-06-23T11:48:28.000+02:00" CHECKSUM="4265c309e3a16aa5ed5781ef2e82f958" CHECKSUMTYPE="MD5">
                    <ns3:FLocat LOCTYPE="OTHER" OTHERLOCTYPE="FILE" ns2:type="simple" ns2:href="page/Turmbuch_StAB B IX 478_00014-20200925_091702.xml"/>
                </ns3:file>
                <ns3:file ID="PAGEXML_15" SEQ="15" MIMETYPE="application/xml" CREATED="2023-06-23T11:48:28.000+02:00" CHECKSUM="e5b79a9a44b5e2a1365e4c4af7764d2b" CHECKSUMTYPE="MD5">
                    <ns3:FLocat LOCTYPE="OTHER" OTHERLOCTYPE="FILE" ns2:type="simple" ns2:href="page/Turmbuch_StAB B IX 478_00015-20200925_091709.xml"/>
                </ns3:file>
                <ns3:file ID="PAGEXML_16" SEQ="16" MIMETYPE="application/xml" CREATED="2023-06-23T11:48:28.000+02:00" CHECKSUM="7204c9953fcac1336fd9539d4baf53f6" CHECKSUMTYPE="MD5">
                    <ns3:FLocat LOCTYPE="OTHER" OTHERLOCTYPE="FILE" ns2:type="simple" ns2:href="page/Turmbuch_StAB B IX 478_00016-20200925_091715.xml"/>
                </ns3:file>
                <ns3:file ID="PAGEXML_17" SEQ="17" MIMETYPE="application/xml" CREATED="2023-06-23T11:48:28.000+02:00" CHECKSUM="45029304c0e0319b99c6529c721eb87a" CHECKSUMTYPE="MD5">
                    <ns3:FLocat LOCTYPE="OTHER" OTHERLOCTYPE="FILE" ns2:type="simple" ns2:href="page/Turmbuch_StAB B IX 478_00017-20200925_091722.xml"/>
                </ns3:file>
                <ns3:file ID="PAGEXML_18" SEQ="18" MIMETYPE="application/xml" CREATED="2023-06-23T11:48:28.000+02:00" CHECKSUM="f9e3589fc15ff5b5c78d42677a44fba2" CHECKSUMTYPE="MD5">
                    <ns3:FLocat LOCTYPE="OTHER" OTHERLOCTYPE="FILE" ns2:type="simple" ns2:href="page/Turmbuch_StAB B IX 478_00018-20200925_091727.xml"/>
                </ns3:file>
                <ns3:file ID="PAGEXML_19" SEQ="19" MIMETYPE="application/xml" CREATED="2023-06-23T11:48:28.000+02:00" CHECKSUM="23af56274c0a82b0bd576eb7f32bbe6f" CHECKSUMTYPE="MD5">
                    <ns3:FLocat LOCTYPE="OTHER" OTHERLOCTYPE="FILE" ns2:type="simple" ns2:href="page/Turmbuch_StAB B IX 478_00019-20200925_091733.xml"/>
                </ns3:file>
                <ns3:file ID="PAGEXML_20" SEQ="20" MIMETYPE="application/xml" CREATED="2023-06-23T11:48:29.000+02:00" CHECKSUM="484a64a026572783430659d160cab966" CHECKSUMTYPE="MD5">
                    <ns3:FLocat LOCTYPE="OTHER" OTHERLOCTYPE="FILE" ns2:type="simple" ns2:href="page/Turmbuch_StAB B IX 478_00020-20200925_091741.xml"/>
                </ns3:file>
                <ns3:file ID="PAGEXML_21" SEQ="21" MIMETYPE="application/xml" CREATED="2023-06-23T11:48:29.000+02:00" CHECKSUM="4935e8c89eb9941162273f2fe9e77484" CHECKSUMTYPE="MD5">
                    <ns3:FLocat LOCTYPE="OTHER" OTHERLOCTYPE="FILE" ns2:type="simple" ns2:href="page/Turmbuch_StAB B IX 478_00021-20200925_091836.xml"/>
                </ns3:file>
                <ns3:file ID="PAGEXML_22" SEQ="22" MIMETYPE="application/xml" CREATED="2023-06-23T11:48:29.000+02:00" CHECKSUM="b4fd6ac6f77aa96b66037a5c7b0937fd" CHECKSUMTYPE="MD5">
                    <ns3:FLocat LOCTYPE="OTHER" OTHERLOCTYPE="FILE" ns2:type="simple" ns2:href="page/Turmbuch_StAB B IX 478_00022-20200925_091844.xml"/>
                </ns3:file>
                <ns3:file ID="PAGEXML_23" SEQ="23" MIMETYPE="application/xml" CREATED="2023-06-23T11:48:29.000+02:00" CHECKSUM="352c7f5761275f0a8452156a170e9545" CHECKSUMTYPE="MD5">
                    <ns3:FLocat LOCTYPE="OTHER" OTHERLOCTYPE="FILE" ns2:type="simple" ns2:href="page/Turmbuch_StAB B IX 478_00023-20200925_091852.xml"/>
                </ns3:file>
                <ns3:file ID="PAGEXML_24" SEQ="24" MIMETYPE="application/xml" CREATED="2023-06-23T11:48:29.000+02:00" CHECKSUM="ded49016025c8d07e5a885fac23e1d67" CHECKSUMTYPE="MD5">
                    <ns3:FLocat LOCTYPE="OTHER" OTHERLOCTYPE="FILE" ns2:type="simple" ns2:href="page/Turmbuch_StAB B IX 478_00024-20200925_091858.xml"/>
                </ns3:file>
                <ns3:file ID="PAGEXML_25" SEQ="25" MIMETYPE="application/xml" CREATED="2023-06-23T11:48:29.000+02:00" CHECKSUM="b7696dc3b6005662f77b84bbc0a424cb" CHECKSUMTYPE="MD5">
                    <ns3:FLocat LOCTYPE="OTHER" OTHERLOCTYPE="FILE" ns2:type="simple" ns2:href="page/Turmbuch_StAB B IX 478_00025-20200925_091905.xml"/>
                </ns3:file>
                <ns3:file ID="PAGEXML_26" SEQ="26" MIMETYPE="application/xml" CREATED="2023-06-23T11:48:29.000+02:00" CHECKSUM="d9217a122a8547a1c31b1546e0382df9" CHECKSUMTYPE="MD5">
                    <ns3:FLocat LOCTYPE="OTHER" OTHERLOCTYPE="FILE" ns2:type="simple" ns2:href="page/Turmbuch_StAB B IX 478_00026-20200925_091912.xml"/>
                </ns3:file>
                <ns3:file ID="PAGEXML_27" SEQ="27" MIMETYPE="application/xml" CREATED="2023-06-23T11:48:29.000+02:00" CHECKSUM="1a75d7c55a5e251452d1e75d5c1faeae" CHECKSUMTYPE="MD5">
                    <ns3:FLocat LOCTYPE="OTHER" OTHERLOCTYPE="FILE" ns2:type="simple" ns2:href="page/Turmbuch_StAB B IX 478_00027-20200925_091918.xml"/>
                </ns3:file>
                <ns3:file ID="PAGEXML_28" SEQ="28" MIMETYPE="application/xml" CREATED="2023-06-23T11:48:31.000+02:00" CHECKSUM="fd77a6431a3865515c76a53a14bf814e" CHECKSUMTYPE="MD5">
                    <ns3:FLocat LOCTYPE="OTHER" OTHERLOCTYPE="FILE" ns2:type="simple" ns2:href="page/Turmbuch_StAB B IX 478_00028-20200925_091924.xml"/>
                </ns3:file>
                <ns3:file ID="PAGEXML_29" SEQ="29" MIMETYPE="application/xml" CREATED="2023-06-23T11:48:31.000+02:00" CHECKSUM="92683ef5d275c9f47f73d0ad30e556f8" CHECKSUMTYPE="MD5">
                    <ns3:FLocat LOCTYPE="OTHER" OTHERLOCTYPE="FILE" ns2:type="simple" ns2:href="page/Turmbuch_StAB B IX 478_00029-20200925_091933.xml"/>
                </ns3:file>
                <ns3:file ID="PAGEXML_30" SEQ="30" MIMETYPE="application/xml" CREATED="2023-06-23T11:48:31.000+02:00" CHECKSUM="09dae28d3c3a0693d902bc47b4bf05db" CHECKSUMTYPE="MD5">
                    <ns3:FLocat LOCTYPE="OTHER" OTHERLOCTYPE="FILE" ns2:type="simple" ns2:href="page/Turmbuch_StAB B IX 478_00030-20200925_091940.xml"/>
                </ns3:file>
                <ns3:file ID="PAGEXML_31" SEQ="31" MIMETYPE="application/xml" CREATED="2023-06-23T11:48:31.000+02:00" CHECKSUM="b02522c8083c20ce8a304196f11fdf5f" CHECKSUMTYPE="MD5">
                    <ns3:FLocat LOCTYPE="OTHER" OTHERLOCTYPE="FILE" ns2:type="simple" ns2:href="page/Turmbuch_StAB B IX 478_00031-20200925_091946.xml"/>
                </ns3:file>
                <ns3:file ID="PAGEXML_32" SEQ="32" MIMETYPE="application/xml" CREATED="2023-06-23T11:48:31.000+02:00" CHECKSUM="2422d8bbd09d9dd07f155f5cb1dad2fe" CHECKSUMTYPE="MD5">
                    <ns3:FLocat LOCTYPE="OTHER" OTHERLOCTYPE="FILE" ns2:type="simple" ns2:href="page/Turmbuch_StAB B IX 478_00032-20200925_092137.xml"/>
                </ns3:file>
                <ns3:file ID="PAGEXML_33" SEQ="33" MIMETYPE="application/xml" CREATED="2023-06-23T11:48:31.000+02:00" CHECKSUM="758f7db19e381458d116ab9e5c54a61e" CHECKSUMTYPE="MD5">
                    <ns3:FLocat LOCTYPE="OTHER" OTHERLOCTYPE="FILE" ns2:type="simple" ns2:href="page/Turmbuch_StAB B IX 478_00033-20200925_092144.xml"/>
                </ns3:file>
                <ns3:file ID="PAGEXML_34" SEQ="34" MIMETYPE="application/xml" CREATED="2023-06-23T11:48:32.000+02:00" CHECKSUM="dbb668ace0b90e40899254c20c51be5c" CHECKSUMTYPE="MD5">
                    <ns3:FLocat LOCTYPE="OTHER" OTHERLOCTYPE="FILE" ns2:type="simple" ns2:href="page/Turmbuch_StAB B IX 478_00034-20200925_092150.xml"/>
                </ns3:file>
                <ns3:file ID="PAGEXML_35" SEQ="35" MIMETYPE="application/xml" CREATED="2023-06-23T11:48:32.000+02:00" CHECKSUM="83f44429b28b7522dd603e9787d606fc" CHECKSUMTYPE="MD5">
                    <ns3:FLocat LOCTYPE="OTHER" OTHERLOCTYPE="FILE" ns2:type="simple" ns2:href="page/Turmbuch_StAB B IX 478_00035-20200925_092157.xml"/>
                </ns3:file>
                <ns3:file ID="PAGEXML_36" SEQ="36" MIMETYPE="application/xml" CREATED="2023-06-23T11:48:32.000+02:00" CHECKSUM="955e691042a5cddc8a65bf7a3bb75f9b" CHECKSUMTYPE="MD5">
                    <ns3:FLocat LOCTYPE="OTHER" OTHERLOCTYPE="FILE" ns2:type="simple" ns2:href="page/Turmbuch_StAB B IX 478_00036-20200925_092204.xml"/>
                </ns3:file>
                <ns3:file ID="PAGEXML_37" SEQ="37" MIMETYPE="application/xml" CREATED="2023-06-23T11:48:32.000+02:00" CHECKSUM="739c412fb1cd1528d167b6706f37d221" CHECKSUMTYPE="MD5">
                    <ns3:FLocat LOCTYPE="OTHER" OTHERLOCTYPE="FILE" ns2:type="simple" ns2:href="page/Turmbuch_StAB B IX 478_00037-20200925_092209.xml"/>
                </ns3:file>
                <ns3:file ID="PAGEXML_38" SEQ="38" MIMETYPE="application/xml" CREATED="2023-06-23T11:48:32.000+02:00" CHECKSUM="9e8d1b90bf2891304224f785c073faaa" CHECKSUMTYPE="MD5">
                    <ns3:FLocat LOCTYPE="OTHER" OTHERLOCTYPE="FILE" ns2:type="simple" ns2:href="page/Turmbuch_StAB B IX 478_00038-20200925_092215.xml"/>
                </ns3:file>
                <ns3:file ID="PAGEXML_39" SEQ="39" MIMETYPE="application/xml" CREATED="2023-06-23T11:48:32.000+02:00" CHECKSUM="c19b9c5d1f8ff7860fb3985d2fbe5c44" CHECKSUMTYPE="MD5">
                    <ns3:FLocat LOCTYPE="OTHER" OTHERLOCTYPE="FILE" ns2:type="simple" ns2:href="page/Turmbuch_StAB B IX 478_00039-20200925_092221.xml"/>
                </ns3:file>
                <ns3:file ID="PAGEXML_40" SEQ="40" MIMETYPE="application/xml" CREATED="2023-06-23T11:48:32.000+02:00" CHECKSUM="a7b2a4da6a9f44a5a73a8d2bccbe7c06" CHECKSUMTYPE="MD5">
                    <ns3:FLocat LOCTYPE="OTHER" OTHERLOCTYPE="FILE" ns2:type="simple" ns2:href="page/Turmbuch_StAB B IX 478_00040-20200925_092226.xml"/>
                </ns3:file>
                <ns3:file ID="PAGEXML_41" SEQ="41" MIMETYPE="application/xml" CREATED="2023-06-23T11:48:32.000+02:00" CHECKSUM="3d301d7b4d0244d2d9ceb16f99959500" CHECKSUMTYPE="MD5">
                    <ns3:FLocat LOCTYPE="OTHER" OTHERLOCTYPE="FILE" ns2:type="simple" ns2:href="page/Turmbuch_StAB B IX 478_00041-20200925_092232.xml"/>
                </ns3:file>
                <ns3:file ID="PAGEXML_42" SEQ="42" MIMETYPE="application/xml" CREATED="2023-06-23T11:48:32.000+02:00" CHECKSUM="3fd74362daf1e890d2cdf41e1559c32a" CHECKSUMTYPE="MD5">
                    <ns3:FLocat LOCTYPE="OTHER" OTHERLOCTYPE="FILE" ns2:type="simple" ns2:href="page/Turmbuch_StAB B IX 478_00042-20200925_092313.xml"/>
                </ns3:file>
                <ns3:file ID="PAGEXML_43" SEQ="43" MIMETYPE="application/xml" CREATED="2023-06-23T11:48:32.000+02:00" CHECKSUM="a36c7e80cd018b245e4e50b0cb406235" CHECKSUMTYPE="MD5">
                    <ns3:FLocat LOCTYPE="OTHER" OTHERLOCTYPE="FILE" ns2:type="simple" ns2:href="page/Turmbuch_StAB B IX 478_00043-20200925_092319.xml"/>
                </ns3:file>
                <ns3:file ID="PAGEXML_44" SEQ="44" MIMETYPE="application/xml" CREATED="2023-06-23T11:48:32.000+02:00" CHECKSUM="3c83f4f8636285b95eff48e390148187" CHECKSUMTYPE="MD5">
                    <ns3:FLocat LOCTYPE="OTHER" OTHERLOCTYPE="FILE" ns2:type="simple" ns2:href="page/Turmbuch_StAB B IX 478_00044-20200925_092324.xml"/>
                </ns3:file>
                <ns3:file ID="PAGEXML_45" SEQ="45" MIMETYPE="application/xml" CREATED="2023-06-23T11:48:32.000+02:00" CHECKSUM="cfc28489fbe9c07626dd24f617448c1e" CHECKSUMTYPE="MD5">
                    <ns3:FLocat LOCTYPE="OTHER" OTHERLOCTYPE="FILE" ns2:type="simple" ns2:href="page/Turmbuch_StAB B IX 478_00045-20200925_092329.xml"/>
                </ns3:file>
                <ns3:file ID="PAGEXML_46" SEQ="46" MIMETYPE="application/xml" CREATED="2023-06-23T11:48:33.000+02:00" CHECKSUM="90b31c1c384863d42971eceea1c0d749" CHECKSUMTYPE="MD5">
                    <ns3:FLocat LOCTYPE="OTHER" OTHERLOCTYPE="FILE" ns2:type="simple" ns2:href="page/Turmbuch_StAB B IX 478_00046-20200925_092334.xml"/>
                </ns3:file>
                <ns3:file ID="PAGEXML_47" SEQ="47" MIMETYPE="application/xml" CREATED="2023-06-23T11:48:33.000+02:00" CHECKSUM="a458a1f916a006b8f43e742a0993930d" CHECKSUMTYPE="MD5">
                    <ns3:FLocat LOCTYPE="OTHER" OTHERLOCTYPE="FILE" ns2:type="simple" ns2:href="page/Turmbuch_StAB B IX 478_00047-20200925_092339.xml"/>
                </ns3:file>
                <ns3:file ID="PAGEXML_48" SEQ="48" MIMETYPE="application/xml" CREATED="2023-06-23T11:48:33.000+02:00" CHECKSUM="f8fb1e0ef3a6dd6d8558d8823473b9cd" CHECKSUMTYPE="MD5">
                    <ns3:FLocat LOCTYPE="OTHER" OTHERLOCTYPE="FILE" ns2:type="simple" ns2:href="page/Turmbuch_StAB B IX 478_00048-20200925_092344.xml"/>
                </ns3:file>
                <ns3:file ID="PAGEXML_49" SEQ="49" MIMETYPE="application/xml" CREATED="2023-06-23T11:48:33.000+02:00" CHECKSUM="7e81fa38cfe0510acde2e3f997b4b648" CHECKSUMTYPE="MD5">
                    <ns3:FLocat LOCTYPE="OTHER" OTHERLOCTYPE="FILE" ns2:type="simple" ns2:href="page/Turmbuch_StAB B IX 478_00049-20200925_092351.xml"/>
                </ns3:file>
                <ns3:file ID="PAGEXML_50" SEQ="50" MIMETYPE="application/xml" CREATED="2023-06-23T11:48:33.000+02:00" CHECKSUM="5454b5e4dba445ff5c919474aab59973" CHECKSUMTYPE="MD5">
                    <ns3:FLocat LOCTYPE="OTHER" OTHERLOCTYPE="FILE" ns2:type="simple" ns2:href="page/Turmbuch_StAB B IX 478_00050-20200925_092358.xml"/>
                </ns3:file>
                <ns3:file ID="PAGEXML_51" SEQ="51" MIMETYPE="application/xml" CREATED="2023-06-23T11:48:33.000+02:00" CHECKSUM="c6e2378593aa2abf3a644cabdaf3e64c" CHECKSUMTYPE="MD5">
                    <ns3:FLocat LOCTYPE="OTHER" OTHERLOCTYPE="FILE" ns2:type="simple" ns2:href="page/Turmbuch_StAB B IX 478_00051-20200925_092405.xml"/>
                </ns3:file>
                <ns3:file ID="PAGEXML_52" SEQ="52" MIMETYPE="application/xml" CREATED="2023-06-23T11:48:33.000+02:00" CHECKSUM="3eca6346fe740c98a62a4c3a1aca37a0" CHECKSUMTYPE="MD5">
                    <ns3:FLocat LOCTYPE="OTHER" OTHERLOCTYPE="FILE" ns2:type="simple" ns2:href="page/Turmbuch_StAB B IX 478_00052-20200925_092411.xml"/>
                </ns3:file>
                <ns3:file ID="PAGEXML_53" SEQ="53" MIMETYPE="application/xml" CREATED="2023-06-23T11:48:33.000+02:00" CHECKSUM="5b683a984c0e9b007d190339bea8396d" CHECKSUMTYPE="MD5">
                    <ns3:FLocat LOCTYPE="OTHER" OTHERLOCTYPE="FILE" ns2:type="simple" ns2:href="page/Turmbuch_StAB B IX 478_00053-20200925_092417.xml"/>
                </ns3:file>
                <ns3:file ID="PAGEXML_54" SEQ="54" MIMETYPE="application/xml" CREATED="2023-06-23T11:48:33.000+02:00" CHECKSUM="a10eb7e66faa713eae472f51aa38630a" CHECKSUMTYPE="MD5">
                    <ns3:FLocat LOCTYPE="OTHER" OTHERLOCTYPE="FILE" ns2:type="simple" ns2:href="page/Turmbuch_StAB B IX 478_00054-20200925_092424.xml"/>
                </ns3:file>
                <ns3:file ID="PAGEXML_55" SEQ="55" MIMETYPE="application/xml" CREATED="2023-06-23T11:48:33.000+02:00" CHECKSUM="dba857247867f5f1faddc18a1118a481" CHECKSUMTYPE="MD5">
                    <ns3:FLocat LOCTYPE="OTHER" OTHERLOCTYPE="FILE" ns2:type="simple" ns2:href="page/Turmbuch_StAB B IX 478_00055-20200925_092428.xml"/>
                </ns3:file>
                <ns3:file ID="PAGEXML_56" SEQ="56" MIMETYPE="application/xml" CREATED="2023-06-23T11:48:33.000+02:00" CHECKSUM="ff64dd1b681080a84f758f780fb6af0a" CHECKSUMTYPE="MD5">
                    <ns3:FLocat LOCTYPE="OTHER" OTHERLOCTYPE="FILE" ns2:type="simple" ns2:href="page/Turmbuch_StAB B IX 478_00056-20200925_092433.xml"/>
                </ns3:file>
                <ns3:file ID="PAGEXML_57" SEQ="57" MIMETYPE="application/xml" CREATED="2023-06-23T11:48:33.000+02:00" CHECKSUM="d802d7736d62315f26afa842bc764e70" CHECKSUMTYPE="MD5">
                    <ns3:FLocat LOCTYPE="OTHER" OTHERLOCTYPE="FILE" ns2:type="simple" ns2:href="page/Turmbuch_StAB B IX 478_00057-20200925_092439.xml"/>
                </ns3:file>
                <ns3:file ID="PAGEXML_58" SEQ="58" MIMETYPE="application/xml" CREATED="2023-06-23T11:48:33.000+02:00" CHECKSUM="bc7e64be9148a8daf5c4a4f687ee338b" CHECKSUMTYPE="MD5">
                    <ns3:FLocat LOCTYPE="OTHER" OTHERLOCTYPE="FILE" ns2:type="simple" ns2:href="page/Turmbuch_StAB B IX 478_00058-20200925_092444.xml"/>
                </ns3:file>
                <ns3:file ID="PAGEXML_59" SEQ="59" MIMETYPE="application/xml" CREATED="2023-06-23T11:48:34.000+02:00" CHECKSUM="d10264809f6f45e3b92d2b77c758aec4" CHECKSUMTYPE="MD5">
                    <ns3:FLocat LOCTYPE="OTHER" OTHERLOCTYPE="FILE" ns2:type="simple" ns2:href="page/Turmbuch_StAB B IX 478_00059-20200925_092450.xml"/>
                </ns3:file>
                <ns3:file ID="PAGEXML_60" SEQ="60" MIMETYPE="application/xml" CREATED="2023-06-23T11:48:34.000+02:00" CHECKSUM="96044ff3e5d76ce7e921c51529951b80" CHECKSUMTYPE="MD5">
                    <ns3:FLocat LOCTYPE="OTHER" OTHERLOCTYPE="FILE" ns2:type="simple" ns2:href="page/Turmbuch_StAB B IX 478_00060-20200925_092455.xml"/>
                </ns3:file>
                <ns3:file ID="PAGEXML_61" SEQ="61" MIMETYPE="application/xml" CREATED="2023-06-23T11:48:34.000+02:00" CHECKSUM="f7292478d29fb9636d66c96c1cfcdfb2" CHECKSUMTYPE="MD5">
                    <ns3:FLocat LOCTYPE="OTHER" OTHERLOCTYPE="FILE" ns2:type="simple" ns2:href="page/Turmbuch_StAB B IX 478_00061-20200925_092501.xml"/>
                </ns3:file>
                <ns3:file ID="PAGEXML_62" SEQ="62" MIMETYPE="application/xml" CREATED="2023-06-23T11:48:34.000+02:00" CHECKSUM="9247a384fa2b7364eca745762575aff7" CHECKSUMTYPE="MD5">
                    <ns3:FLocat LOCTYPE="OTHER" OTHERLOCTYPE="FILE" ns2:type="simple" ns2:href="page/Turmbuch_StAB B IX 478_00062-20200925_092507.xml"/>
                </ns3:file>
                <ns3:file ID="PAGEXML_63" SEQ="63" MIMETYPE="application/xml" CREATED="2023-06-23T11:48:34.000+02:00" CHECKSUM="d7bdd3c36389b228f2f326a139aa5ada" CHECKSUMTYPE="MD5">
                    <ns3:FLocat LOCTYPE="OTHER" OTHERLOCTYPE="FILE" ns2:type="simple" ns2:href="page/Turmbuch_StAB B IX 478_00063-20200925_092512.xml"/>
                </ns3:file>
                <ns3:file ID="PAGEXML_64" SEQ="64" MIMETYPE="application/xml" CREATED="2023-06-23T11:48:34.000+02:00" CHECKSUM="4a6a4536683e8c9452a9928fba90199a" CHECKSUMTYPE="MD5">
                    <ns3:FLocat LOCTYPE="OTHER" OTHERLOCTYPE="FILE" ns2:type="simple" ns2:href="page/Turmbuch_StAB B IX 478_00064-20200925_092517.xml"/>
                </ns3:file>
                <ns3:file ID="PAGEXML_65" SEQ="65" MIMETYPE="application/xml" CREATED="2023-06-23T11:48:34.000+02:00" CHECKSUM="d9fdc60e6718b9f52404c227a0b3cf0f" CHECKSUMTYPE="MD5">
                    <ns3:FLocat LOCTYPE="OTHER" OTHERLOCTYPE="FILE" ns2:type="simple" ns2:href="page/Turmbuch_StAB B IX 478_00065-20200925_092522.xml"/>
                </ns3:file>
                <ns3:file ID="PAGEXML_66" SEQ="66" MIMETYPE="application/xml" CREATED="2023-06-23T11:48:34.000+02:00" CHECKSUM="b01d744e85768f66ca46a8252df0068a" CHECKSUMTYPE="MD5">
                    <ns3:FLocat LOCTYPE="OTHER" OTHERLOCTYPE="FILE" ns2:type="simple" ns2:href="page/Turmbuch_StAB B IX 478_00066-20200925_092527.xml"/>
                </ns3:file>
                <ns3:file ID="PAGEXML_67" SEQ="67" MIMETYPE="application/xml" CREATED="2023-06-23T11:48:34.000+02:00" CHECKSUM="56554d9c10738a58754d6f108d45b283" CHECKSUMTYPE="MD5">
                    <ns3:FLocat LOCTYPE="OTHER" OTHERLOCTYPE="FILE" ns2:type="simple" ns2:href="page/Turmbuch_StAB B IX 478_00067-20200925_092532.xml"/>
                </ns3:file>
                <ns3:file ID="PAGEXML_68" SEQ="68" MIMETYPE="application/xml" CREATED="2023-06-23T11:48:34.000+02:00" CHECKSUM="c959102564a37a7f0205702883d41e69" CHECKSUMTYPE="MD5">
                    <ns3:FLocat LOCTYPE="OTHER" OTHERLOCTYPE="FILE" ns2:type="simple" ns2:href="page/Turmbuch_StAB B IX 478_00068-20200925_092537.xml"/>
                </ns3:file>
                <ns3:file ID="PAGEXML_69" SEQ="69" MIMETYPE="application/xml" CREATED="2023-06-23T11:48:34.000+02:00" CHECKSUM="585aa9730c034048a1c36095b66d5144" CHECKSUMTYPE="MD5">
                    <ns3:FLocat LOCTYPE="OTHER" OTHERLOCTYPE="FILE" ns2:type="simple" ns2:href="page/Turmbuch_StAB B IX 478_00069-20200925_092543.xml"/>
                </ns3:file>
                <ns3:file ID="PAGEXML_70" SEQ="70" MIMETYPE="application/xml" CREATED="2023-06-23T11:48:34.000+02:00" CHECKSUM="e710a441759632e3a42be70245ee4b34" CHECKSUMTYPE="MD5">
                    <ns3:FLocat LOCTYPE="OTHER" OTHERLOCTYPE="FILE" ns2:type="simple" ns2:href="page/Turmbuch_StAB B IX 478_00070-20200925_092547.xml"/>
                </ns3:file>
                <ns3:file ID="PAGEXML_71" SEQ="71" MIMETYPE="application/xml" CREATED="2023-06-23T11:48:34.000+02:00" CHECKSUM="a648e60a7477a3b91272e74aa641490f" CHECKSUMTYPE="MD5">
                    <ns3:FLocat LOCTYPE="OTHER" OTHERLOCTYPE="FILE" ns2:type="simple" ns2:href="page/Turmbuch_StAB B IX 478_00071-20200925_092552.xml"/>
                </ns3:file>
                <ns3:file ID="PAGEXML_72" SEQ="72" MIMETYPE="application/xml" CREATED="2023-06-23T11:48:34.000+02:00" CHECKSUM="83c5321c8116bb0fc062b120e3f28fb7" CHECKSUMTYPE="MD5">
                    <ns3:FLocat LOCTYPE="OTHER" OTHERLOCTYPE="FILE" ns2:type="simple" ns2:href="page/Turmbuch_StAB B IX 478_00072-20200925_092557.xml"/>
                </ns3:file>
                <ns3:file ID="PAGEXML_73" SEQ="73" MIMETYPE="application/xml" CREATED="2023-06-23T11:48:34.000+02:00" CHECKSUM="21f431a3a240f19aa1914c8d2792a0a5" CHECKSUMTYPE="MD5">
                    <ns3:FLocat LOCTYPE="OTHER" OTHERLOCTYPE="FILE" ns2:type="simple" ns2:href="page/Turmbuch_StAB B IX 478_00073-20200925_092602.xml"/>
                </ns3:file>
                <ns3:file ID="PAGEXML_74" SEQ="74" MIMETYPE="application/xml" CREATED="2023-06-23T11:48:34.000+02:00" CHECKSUM="f8b7d2db104edb569a6a325c25d181aa" CHECKSUMTYPE="MD5">
                    <ns3:FLocat LOCTYPE="OTHER" OTHERLOCTYPE="FILE" ns2:type="simple" ns2:href="page/Turmbuch_StAB B IX 478_00074-20200925_092607.xml"/>
                </ns3:file>
                <ns3:file ID="PAGEXML_75" SEQ="75" MIMETYPE="application/xml" CREATED="2023-06-23T11:48:34.000+02:00" CHECKSUM="55912da866b3adb505529a777cbe3d71" CHECKSUMTYPE="MD5">
                    <ns3:FLocat LOCTYPE="OTHER" OTHERLOCTYPE="FILE" ns2:type="simple" ns2:href="page/Turmbuch_StAB B IX 478_00075-20200925_092612.xml"/>
                </ns3:file>
                <ns3:file ID="PAGEXML_76" SEQ="76" MIMETYPE="application/xml" CREATED="2023-06-23T11:48:34.000+02:00" CHECKSUM="0fd3139c008ac76208c51b0ae12b08eb" CHECKSUMTYPE="MD5">
                    <ns3:FLocat LOCTYPE="OTHER" OTHERLOCTYPE="FILE" ns2:type="simple" ns2:href="page/Turmbuch_StAB B IX 478_00076-20200925_092616.xml"/>
                </ns3:file>
                <ns3:file ID="PAGEXML_77" SEQ="77" MIMETYPE="application/xml" CREATED="2023-06-23T11:48:34.000+02:00" CHECKSUM="866c976fe21f78edf0f61f8d7256189c" CHECKSUMTYPE="MD5">
                    <ns3:FLocat LOCTYPE="OTHER" OTHERLOCTYPE="FILE" ns2:type="simple" ns2:href="page/Turmbuch_StAB B IX 478_00077-20200925_092621.xml"/>
                </ns3:file>
                <ns3:file ID="PAGEXML_78" SEQ="78" MIMETYPE="application/xml" CREATED="2023-06-23T11:48:35.000+02:00" CHECKSUM="f179d6194c8efd53e57c828c482a7443" CHECKSUMTYPE="MD5">
                    <ns3:FLocat LOCTYPE="OTHER" OTHERLOCTYPE="FILE" ns2:type="simple" ns2:href="page/Turmbuch_StAB B IX 478_00078-20200925_092627.xml"/>
                </ns3:file>
                <ns3:file ID="PAGEXML_79" SEQ="79" MIMETYPE="application/xml" CREATED="2023-06-23T11:48:35.000+02:00" CHECKSUM="1751c78ad6c1e52ed8bf4541d7b3fe57" CHECKSUMTYPE="MD5">
                    <ns3:FLocat LOCTYPE="OTHER" OTHERLOCTYPE="FILE" ns2:type="simple" ns2:href="page/Turmbuch_StAB B IX 478_00079-20200925_092632.xml"/>
                </ns3:file>
                <ns3:file ID="PAGEXML_80" SEQ="80" MIMETYPE="application/xml" CREATED="2023-06-23T11:48:35.000+02:00" CHECKSUM="4ce5ba8a3c8f478a8997ed0e026d10d7" CHECKSUMTYPE="MD5">
                    <ns3:FLocat LOCTYPE="OTHER" OTHERLOCTYPE="FILE" ns2:type="simple" ns2:href="page/Turmbuch_StAB B IX 478_00080-20200925_092636.xml"/>
                </ns3:file>
                <ns3:file ID="PAGEXML_81" SEQ="81" MIMETYPE="application/xml" CREATED="2023-06-23T11:48:35.000+02:00" CHECKSUM="d36d48bb33684b01c9be5367622438c7" CHECKSUMTYPE="MD5">
                    <ns3:FLocat LOCTYPE="OTHER" OTHERLOCTYPE="FILE" ns2:type="simple" ns2:href="page/Turmbuch_StAB B IX 478_00081-20200925_092644.xml"/>
                </ns3:file>
                <ns3:file ID="PAGEXML_82" SEQ="82" MIMETYPE="application/xml" CREATED="2023-06-23T11:48:35.000+02:00" CHECKSUM="364451ceeb5d36225f4aadefdd34d2e3" CHECKSUMTYPE="MD5">
                    <ns3:FLocat LOCTYPE="OTHER" OTHERLOCTYPE="FILE" ns2:type="simple" ns2:href="page/Turmbuch_StAB B IX 478_00082-20200925_092651.xml"/>
                </ns3:file>
                <ns3:file ID="PAGEXML_83" SEQ="83" MIMETYPE="application/xml" CREATED="2023-06-23T11:48:35.000+02:00" CHECKSUM="a9309626a546d53f0baff23047bf9bad" CHECKSUMTYPE="MD5">
                    <ns3:FLocat LOCTYPE="OTHER" OTHERLOCTYPE="FILE" ns2:type="simple" ns2:href="page/Turmbuch_StAB B IX 478_00083-20200925_092656.xml"/>
                </ns3:file>
                <ns3:file ID="PAGEXML_84" SEQ="84" MIMETYPE="application/xml" CREATED="2023-06-23T11:48:35.000+02:00" CHECKSUM="e0472810d20f7fd6792615d02bb7d886" CHECKSUMTYPE="MD5">
                    <ns3:FLocat LOCTYPE="OTHER" OTHERLOCTYPE="FILE" ns2:type="simple" ns2:href="page/Turmbuch_StAB B IX 478_00084-20200925_092701.xml"/>
                </ns3:file>
                <ns3:file ID="PAGEXML_85" SEQ="85" MIMETYPE="application/xml" CREATED="2023-06-23T11:48:35.000+02:00" CHECKSUM="ed92eebb46be2a633f5a7af1fd607fca" CHECKSUMTYPE="MD5">
                    <ns3:FLocat LOCTYPE="OTHER" OTHERLOCTYPE="FILE" ns2:type="simple" ns2:href="page/Turmbuch_StAB B IX 478_00085-20200925_092706.xml"/>
                </ns3:file>
                <ns3:file ID="PAGEXML_86" SEQ="86" MIMETYPE="application/xml" CREATED="2023-06-23T11:48:35.000+02:00" CHECKSUM="cb1198abf8090cf29dd03a1fd6479b0a" CHECKSUMTYPE="MD5">
                    <ns3:FLocat LOCTYPE="OTHER" OTHERLOCTYPE="FILE" ns2:type="simple" ns2:href="page/Turmbuch_StAB B IX 478_00086-20200925_092711.xml"/>
                </ns3:file>
                <ns3:file ID="PAGEXML_87" SEQ="87" MIMETYPE="application/xml" CREATED="2023-06-23T11:48:35.000+02:00" CHECKSUM="f0654b2bac3e1287bd3e86257ab2c5b4" CHECKSUMTYPE="MD5">
                    <ns3:FLocat LOCTYPE="OTHER" OTHERLOCTYPE="FILE" ns2:type="simple" ns2:href="page/Turmbuch_StAB B IX 478_00087-20200925_092716.xml"/>
                </ns3:file>
                <ns3:file ID="PAGEXML_88" SEQ="88" MIMETYPE="application/xml" CREATED="2023-06-23T11:48:35.000+02:00" CHECKSUM="a4d5c825193cc2957ef7ea74b2f9a7d6" CHECKSUMTYPE="MD5">
                    <ns3:FLocat LOCTYPE="OTHER" OTHERLOCTYPE="FILE" ns2:type="simple" ns2:href="page/Turmbuch_StAB B IX 478_00088-20200925_092721.xml"/>
                </ns3:file>
                <ns3:file ID="PAGEXML_89" SEQ="89" MIMETYPE="application/xml" CREATED="2023-06-23T11:48:36.000+02:00" CHECKSUM="0a9daf3039a1e5a338b88d11e60249ab" CHECKSUMTYPE="MD5">
                    <ns3:FLocat LOCTYPE="OTHER" OTHERLOCTYPE="FILE" ns2:type="simple" ns2:href="page/Turmbuch_StAB B IX 478_00089-20200925_092726.xml"/>
                </ns3:file>
                <ns3:file ID="PAGEXML_90" SEQ="90" MIMETYPE="application/xml" CREATED="2023-06-23T11:48:36.000+02:00" CHECKSUM="8e413541b6e70d30386cdbe0b80d6dfa" CHECKSUMTYPE="MD5">
                    <ns3:FLocat LOCTYPE="OTHER" OTHERLOCTYPE="FILE" ns2:type="simple" ns2:href="page/Turmbuch_StAB B IX 478_00090-20200925_092731.xml"/>
                </ns3:file>
                <ns3:file ID="PAGEXML_91" SEQ="91" MIMETYPE="application/xml" CREATED="2023-06-23T11:48:36.000+02:00" CHECKSUM="552989d90bf9419a6de52c037221e753" CHECKSUMTYPE="MD5">
                    <ns3:FLocat LOCTYPE="OTHER" OTHERLOCTYPE="FILE" ns2:type="simple" ns2:href="page/Turmbuch_StAB B IX 478_00091-20200925_092737.xml"/>
                </ns3:file>
                <ns3:file ID="PAGEXML_92" SEQ="92" MIMETYPE="application/xml" CREATED="2023-06-23T11:48:36.000+02:00" CHECKSUM="e3897176ada041202fbc60642e4b9039" CHECKSUMTYPE="MD5">
                    <ns3:FLocat LOCTYPE="OTHER" OTHERLOCTYPE="FILE" ns2:type="simple" ns2:href="page/Turmbuch_StAB B IX 478_00092-20200925_092743.xml"/>
                </ns3:file>
                <ns3:file ID="PAGEXML_93" SEQ="93" MIMETYPE="application/xml" CREATED="2023-06-23T11:48:36.000+02:00" CHECKSUM="c5d65470f80e43e25a53b6c71ccf8575" CHECKSUMTYPE="MD5">
                    <ns3:FLocat LOCTYPE="OTHER" OTHERLOCTYPE="FILE" ns2:type="simple" ns2:href="page/Turmbuch_StAB B IX 478_00093-20200925_092807.xml"/>
                </ns3:file>
                <ns3:file ID="PAGEXML_94" SEQ="94" MIMETYPE="application/xml" CREATED="2023-06-23T11:48:36.000+02:00" CHECKSUM="2e87d116e628c619c38886f22ad13737" CHECKSUMTYPE="MD5">
                    <ns3:FLocat LOCTYPE="OTHER" OTHERLOCTYPE="FILE" ns2:type="simple" ns2:href="page/Turmbuch_StAB B IX 478_00094-20200925_092816.xml"/>
                </ns3:file>
                <ns3:file ID="PAGEXML_95" SEQ="95" MIMETYPE="application/xml" CREATED="2023-06-23T11:48:36.000+02:00" CHECKSUM="cb80595fb9090f3e9b511c90e9f003cf" CHECKSUMTYPE="MD5">
                    <ns3:FLocat LOCTYPE="OTHER" OTHERLOCTYPE="FILE" ns2:type="simple" ns2:href="page/Turmbuch_StAB B IX 478_00095-20200925_092823.xml"/>
                </ns3:file>
                <ns3:file ID="PAGEXML_96" SEQ="96" MIMETYPE="application/xml" CREATED="2023-06-23T11:48:36.000+02:00" CHECKSUM="d47624f1fff30405ceb0b34ecfaf1b91" CHECKSUMTYPE="MD5">
                    <ns3:FLocat LOCTYPE="OTHER" OTHERLOCTYPE="FILE" ns2:type="simple" ns2:href="page/Turmbuch_StAB B IX 478_00096-20200925_092830.xml"/>
                </ns3:file>
                <ns3:file ID="PAGEXML_97" SEQ="97" MIMETYPE="application/xml" CREATED="2023-06-23T11:48:36.000+02:00" CHECKSUM="56fa79b02d01ee635f084b0d13192f75" CHECKSUMTYPE="MD5">
                    <ns3:FLocat LOCTYPE="OTHER" OTHERLOCTYPE="FILE" ns2:type="simple" ns2:href="page/Turmbuch_StAB B IX 478_00097-20200925_092836.xml"/>
                </ns3:file>
                <ns3:file ID="PAGEXML_98" SEQ="98" MIMETYPE="application/xml" CREATED="2023-06-23T11:48:36.000+02:00" CHECKSUM="bd43297f22a943a98f5ff0edd88d82fb" CHECKSUMTYPE="MD5">
                    <ns3:FLocat LOCTYPE="OTHER" OTHERLOCTYPE="FILE" ns2:type="simple" ns2:href="page/Turmbuch_StAB B IX 478_00098-20200925_092841.xml"/>
                </ns3:file>
                <ns3:file ID="PAGEXML_99" SEQ="99" MIMETYPE="application/xml" CREATED="2023-06-23T11:48:36.000+02:00" CHECKSUM="c0176354f81bfa67acb92f94a8c04b42" CHECKSUMTYPE="MD5">
                    <ns3:FLocat LOCTYPE="OTHER" OTHERLOCTYPE="FILE" ns2:type="simple" ns2:href="page/Turmbuch_StAB B IX 478_00099-20200925_092848.xml"/>
                </ns3:file>
            </ns3:fileGrp>
        </ns3:fileGrp>
    </ns3:fileSec>
    <ns3:structMap ID="TRP_STRUCTMAP" TYPE="MANUSCRIPT">
        <ns3:div ID="TRP_DOC_DIV" ADMID="MD_ORIG">
            <ns3:div ID="PAGE_1" ORDER="1" TYPE="SINGLE_PAGE">
                <ns3:fptr>
                    <ns3:area FILEID="PAGEXML_1"/>
                </ns3:fptr>
            </ns3:div>
            <ns3:div ID="PAGE_2" ORDER="2" TYPE="SINGLE_PAGE">
                <ns3:fptr>
                    <ns3:area FILEID="PAGEXML_2"/>
                </ns3:fptr>
            </ns3:div>
            <ns3:div ID="PAGE_3" ORDER="3" TYPE="SINGLE_PAGE">
                <ns3:fptr>
                    <ns3:area FILEID="PAGEXML_3"/>
                </ns3:fptr>
            </ns3:div>
            <ns3:div ID="PAGE_4" ORDER="4" TYPE="SINGLE_PAGE">
                <ns3:fptr>
                    <ns3:area FILEID="PAGEXML_4"/>
                </ns3:fptr>
            </ns3:div>
            <ns3:div ID="PAGE_5" ORDER="5" TYPE="SINGLE_PAGE">
                <ns3:fptr>
                    <ns3:area FILEID="PAGEXML_5"/>
                </ns3:fptr>
            </ns3:div>
            <ns3:div ID="PAGE_6" ORDER="6" TYPE="SINGLE_PAGE">
                <ns3:fptr>
                    <ns3:area FILEID="PAGEXML_6"/>
                </ns3:fptr>
            </ns3:div>
            <ns3:div ID="PAGE_7" ORDER="7" TYPE="SINGLE_PAGE">
                <ns3:fptr>
                    <ns3:area FILEID="PAGEXML_7"/>
                </ns3:fptr>
            </ns3:div>
            <ns3:div ID="PAGE_8" ORDER="8" TYPE="SINGLE_PAGE">
                <ns3:fptr>
                    <ns3:area FILEID="PAGEXML_8"/>
                </ns3:fptr>
            </ns3:div>
            <ns3:div ID="PAGE_9" ORDER="9" TYPE="SINGLE_PAGE">
                <ns3:fptr>
                    <ns3:area FILEID="PAGEXML_9"/>
                </ns3:fptr>
            </ns3:div>
            <ns3:div ID="PAGE_10" ORDER="10" TYPE="SINGLE_PAGE">
                <ns3:fptr>
                    <ns3:area FILEID="PAGEXML_10"/>
                </ns3:fptr>
            </ns3:div>
            <ns3:div ID="PAGE_11" ORDER="11" TYPE="SINGLE_PAGE">
                <ns3:fptr>
                    <ns3:area FILEID="PAGEXML_11"/>
                </ns3:fptr>
            </ns3:div>
            <ns3:div ID="PAGE_12" ORDER="12" TYPE="SINGLE_PAGE">
                <ns3:fptr>
                    <ns3:area FILEID="PAGEXML_12"/>
                </ns3:fptr>
            </ns3:div>
            <ns3:div ID="PAGE_13" ORDER="13" TYPE="SINGLE_PAGE">
                <ns3:fptr>
                    <ns3:area FILEID="PAGEXML_13"/>
                </ns3:fptr>
            </ns3:div>
            <ns3:div ID="PAGE_14" ORDER="14" TYPE="SINGLE_PAGE">
                <ns3:fptr>
                    <ns3:area FILEID="PAGEXML_14"/>
                </ns3:fptr>
            </ns3:div>
            <ns3:div ID="PAGE_15" ORDER="15" TYPE="SINGLE_PAGE">
                <ns3:fptr>
                    <ns3:area FILEID="PAGEXML_15"/>
                </ns3:fptr>
            </ns3:div>
            <ns3:div ID="PAGE_16" ORDER="16" TYPE="SINGLE_PAGE">
                <ns3:fptr>
                    <ns3:area FILEID="PAGEXML_16"/>
                </ns3:fptr>
            </ns3:div>
            <ns3:div ID="PAGE_17" ORDER="17" TYPE="SINGLE_PAGE">
                <ns3:fptr>
                    <ns3:area FILEID="PAGEXML_17"/>
                </ns3:fptr>
            </ns3:div>
            <ns3:div ID="PAGE_18" ORDER="18" TYPE="SINGLE_PAGE">
                <ns3:fptr>
                    <ns3:area FILEID="PAGEXML_18"/>
                </ns3:fptr>
            </ns3:div>
            <ns3:div ID="PAGE_19" ORDER="19" TYPE="SINGLE_PAGE">
                <ns3:fptr>
                    <ns3:area FILEID="PAGEXML_19"/>
                </ns3:fptr>
            </ns3:div>
            <ns3:div ID="PAGE_20" ORDER="20" TYPE="SINGLE_PAGE">
                <ns3:fptr>
                    <ns3:area FILEID="PAGEXML_20"/>
                </ns3:fptr>
            </ns3:div>
            <ns3:div ID="PAGE_21" ORDER="21" TYPE="SINGLE_PAGE">
                <ns3:fptr>
                    <ns3:area FILEID="PAGEXML_21"/>
                </ns3:fptr>
            </ns3:div>
            <ns3:div ID="PAGE_22" ORDER="22" TYPE="SINGLE_PAGE">
                <ns3:fptr>
                    <ns3:area FILEID="PAGEXML_22"/>
                </ns3:fptr>
            </ns3:div>
            <ns3:div ID="PAGE_23" ORDER="23" TYPE="SINGLE_PAGE">
                <ns3:fptr>
                    <ns3:area FILEID="PAGEXML_23"/>
                </ns3:fptr>
            </ns3:div>
            <ns3:div ID="PAGE_24" ORDER="24" TYPE="SINGLE_PAGE">
                <ns3:fptr>
                    <ns3:area FILEID="PAGEXML_24"/>
                </ns3:fptr>
            </ns3:div>
            <ns3:div ID="PAGE_25" ORDER="25" TYPE="SINGLE_PAGE">
                <ns3:fptr>
                    <ns3:area FILEID="PAGEXML_25"/>
                </ns3:fptr>
            </ns3:div>
            <ns3:div ID="PAGE_26" ORDER="26" TYPE="SINGLE_PAGE">
                <ns3:fptr>
                    <ns3:area FILEID="PAGEXML_26"/>
                </ns3:fptr>
            </ns3:div>
            <ns3:div ID="PAGE_27" ORDER="27" TYPE="SINGLE_PAGE">
                <ns3:fptr>
                    <ns3:area FILEID="PAGEXML_27"/>
                </ns3:fptr>
            </ns3:div>
            <ns3:div ID="PAGE_28" ORDER="28" TYPE="SINGLE_PAGE">
                <ns3:fptr>
                    <ns3:area FILEID="PAGEXML_28"/>
                </ns3:fptr>
            </ns3:div>
            <ns3:div ID="PAGE_29" ORDER="29" TYPE="SINGLE_PAGE">
                <ns3:fptr>
                    <ns3:area FILEID="PAGEXML_29"/>
                </ns3:fptr>
            </ns3:div>
            <ns3:div ID="PAGE_30" ORDER="30" TYPE="SINGLE_PAGE">
                <ns3:fptr>
                    <ns3:area FILEID="PAGEXML_30"/>
                </ns3:fptr>
            </ns3:div>
            <ns3:div ID="PAGE_31" ORDER="31" TYPE="SINGLE_PAGE">
                <ns3:fptr>
                    <ns3:area FILEID="PAGEXML_31"/>
                </ns3:fptr>
            </ns3:div>
            <ns3:div ID="PAGE_32" ORDER="32" TYPE="SINGLE_PAGE">
                <ns3:fptr>
                    <ns3:area FILEID="PAGEXML_32"/>
                </ns3:fptr>
            </ns3:div>
            <ns3:div ID="PAGE_33" ORDER="33" TYPE="SINGLE_PAGE">
                <ns3:fptr>
                    <ns3:area FILEID="PAGEXML_33"/>
                </ns3:fptr>
            </ns3:div>
            <ns3:div ID="PAGE_34" ORDER="34" TYPE="SINGLE_PAGE">
                <ns3:fptr>
                    <ns3:area FILEID="PAGEXML_34"/>
                </ns3:fptr>
            </ns3:div>
            <ns3:div ID="PAGE_35" ORDER="35" TYPE="SINGLE_PAGE">
                <ns3:fptr>
                    <ns3:area FILEID="PAGEXML_35"/>
                </ns3:fptr>
            </ns3:div>
            <ns3:div ID="PAGE_36" ORDER="36" TYPE="SINGLE_PAGE">
                <ns3:fptr>
                    <ns3:area FILEID="PAGEXML_36"/>
                </ns3:fptr>
            </ns3:div>
            <ns3:div ID="PAGE_37" ORDER="37" TYPE="SINGLE_PAGE">
                <ns3:fptr>
                    <ns3:area FILEID="PAGEXML_37"/>
                </ns3:fptr>
            </ns3:div>
            <ns3:div ID="PAGE_38" ORDER="38" TYPE="SINGLE_PAGE">
                <ns3:fptr>
                    <ns3:area FILEID="PAGEXML_38"/>
                </ns3:fptr>
            </ns3:div>
            <ns3:div ID="PAGE_39" ORDER="39" TYPE="SINGLE_PAGE">
                <ns3:fptr>
                    <ns3:area FILEID="PAGEXML_39"/>
                </ns3:fptr>
            </ns3:div>
            <ns3:div ID="PAGE_40" ORDER="40" TYPE="SINGLE_PAGE">
                <ns3:fptr>
                    <ns3:area FILEID="PAGEXML_40"/>
                </ns3:fptr>
            </ns3:div>
            <ns3:div ID="PAGE_41" ORDER="41" TYPE="SINGLE_PAGE">
                <ns3:fptr>
                    <ns3:area FILEID="PAGEXML_41"/>
                </ns3:fptr>
            </ns3:div>
            <ns3:div ID="PAGE_42" ORDER="42" TYPE="SINGLE_PAGE">
                <ns3:fptr>
                    <ns3:area FILEID="PAGEXML_42"/>
                </ns3:fptr>
            </ns3:div>
            <ns3:div ID="PAGE_43" ORDER="43" TYPE="SINGLE_PAGE">
                <ns3:fptr>
                    <ns3:area FILEID="PAGEXML_43"/>
                </ns3:fptr>
            </ns3:div>
            <ns3:div ID="PAGE_44" ORDER="44" TYPE="SINGLE_PAGE">
                <ns3:fptr>
                    <ns3:area FILEID="PAGEXML_44"/>
                </ns3:fptr>
            </ns3:div>
            <ns3:div ID="PAGE_45" ORDER="45" TYPE="SINGLE_PAGE">
                <ns3:fptr>
                    <ns3:area FILEID="PAGEXML_45"/>
                </ns3:fptr>
            </ns3:div>
            <ns3:div ID="PAGE_46" ORDER="46" TYPE="SINGLE_PAGE">
                <ns3:fptr>
                    <ns3:area FILEID="PAGEXML_46"/>
                </ns3:fptr>
            </ns3:div>
            <ns3:div ID="PAGE_47" ORDER="47" TYPE="SINGLE_PAGE">
                <ns3:fptr>
                    <ns3:area FILEID="PAGEXML_47"/>
                </ns3:fptr>
            </ns3:div>
            <ns3:div ID="PAGE_48" ORDER="48" TYPE="SINGLE_PAGE">
                <ns3:fptr>
                    <ns3:area FILEID="PAGEXML_48"/>
                </ns3:fptr>
            </ns3:div>
            <ns3:div ID="PAGE_49" ORDER="49" TYPE="SINGLE_PAGE">
                <ns3:fptr>
                    <ns3:area FILEID="PAGEXML_49"/>
                </ns3:fptr>
            </ns3:div>
            <ns3:div ID="PAGE_50" ORDER="50" TYPE="SINGLE_PAGE">
                <ns3:fptr>
                    <ns3:area FILEID="PAGEXML_50"/>
                </ns3:fptr>
            </ns3:div>
            <ns3:div ID="PAGE_51" ORDER="51" TYPE="SINGLE_PAGE">
                <ns3:fptr>
                    <ns3:area FILEID="PAGEXML_51"/>
                </ns3:fptr>
            </ns3:div>
            <ns3:div ID="PAGE_52" ORDER="52" TYPE="SINGLE_PAGE">
                <ns3:fptr>
                    <ns3:area FILEID="PAGEXML_52"/>
                </ns3:fptr>
            </ns3:div>
            <ns3:div ID="PAGE_53" ORDER="53" TYPE="SINGLE_PAGE">
                <ns3:fptr>
                    <ns3:area FILEID="PAGEXML_53"/>
                </ns3:fptr>
            </ns3:div>
            <ns3:div ID="PAGE_54" ORDER="54" TYPE="SINGLE_PAGE">
                <ns3:fptr>
                    <ns3:area FILEID="PAGEXML_54"/>
                </ns3:fptr>
            </ns3:div>
            <ns3:div ID="PAGE_55" ORDER="55" TYPE="SINGLE_PAGE">
                <ns3:fptr>
                    <ns3:area FILEID="PAGEXML_55"/>
                </ns3:fptr>
            </ns3:div>
            <ns3:div ID="PAGE_56" ORDER="56" TYPE="SINGLE_PAGE">
                <ns3:fptr>
                    <ns3:area FILEID="PAGEXML_56"/>
                </ns3:fptr>
            </ns3:div>
            <ns3:div ID="PAGE_57" ORDER="57" TYPE="SINGLE_PAGE">
                <ns3:fptr>
                    <ns3:area FILEID="PAGEXML_57"/>
                </ns3:fptr>
            </ns3:div>
            <ns3:div ID="PAGE_58" ORDER="58" TYPE="SINGLE_PAGE">
                <ns3:fptr>
                    <ns3:area FILEID="PAGEXML_58"/>
                </ns3:fptr>
            </ns3:div>
            <ns3:div ID="PAGE_59" ORDER="59" TYPE="SINGLE_PAGE">
                <ns3:fptr>
                    <ns3:area FILEID="PAGEXML_59"/>
                </ns3:fptr>
            </ns3:div>
            <ns3:div ID="PAGE_60" ORDER="60" TYPE="SINGLE_PAGE">
                <ns3:fptr>
                    <ns3:area FILEID="PAGEXML_60"/>
                </ns3:fptr>
            </ns3:div>
            <ns3:div ID="PAGE_61" ORDER="61" TYPE="SINGLE_PAGE">
                <ns3:fptr>
                    <ns3:area FILEID="PAGEXML_61"/>
                </ns3:fptr>
            </ns3:div>
            <ns3:div ID="PAGE_62" ORDER="62" TYPE="SINGLE_PAGE">
                <ns3:fptr>
                    <ns3:area FILEID="PAGEXML_62"/>
                </ns3:fptr>
            </ns3:div>
            <ns3:div ID="PAGE_63" ORDER="63" TYPE="SINGLE_PAGE">
                <ns3:fptr>
                    <ns3:area FILEID="PAGEXML_63"/>
                </ns3:fptr>
            </ns3:div>
            <ns3:div ID="PAGE_64" ORDER="64" TYPE="SINGLE_PAGE">
                <ns3:fptr>
                    <ns3:area FILEID="PAGEXML_64"/>
                </ns3:fptr>
            </ns3:div>
            <ns3:div ID="PAGE_65" ORDER="65" TYPE="SINGLE_PAGE">
                <ns3:fptr>
                    <ns3:area FILEID="PAGEXML_65"/>
                </ns3:fptr>
            </ns3:div>
            <ns3:div ID="PAGE_66" ORDER="66" TYPE="SINGLE_PAGE">
                <ns3:fptr>
                    <ns3:area FILEID="PAGEXML_66"/>
                </ns3:fptr>
            </ns3:div>
            <ns3:div ID="PAGE_67" ORDER="67" TYPE="SINGLE_PAGE">
                <ns3:fptr>
                    <ns3:area FILEID="PAGEXML_67"/>
                </ns3:fptr>
            </ns3:div>
            <ns3:div ID="PAGE_68" ORDER="68" TYPE="SINGLE_PAGE">
                <ns3:fptr>
                    <ns3:area FILEID="PAGEXML_68"/>
                </ns3:fptr>
            </ns3:div>
            <ns3:div ID="PAGE_69" ORDER="69" TYPE="SINGLE_PAGE">
                <ns3:fptr>
                    <ns3:area FILEID="PAGEXML_69"/>
                </ns3:fptr>
            </ns3:div>
            <ns3:div ID="PAGE_70" ORDER="70" TYPE="SINGLE_PAGE">
                <ns3:fptr>
                    <ns3:area FILEID="PAGEXML_70"/>
                </ns3:fptr>
            </ns3:div>
            <ns3:div ID="PAGE_71" ORDER="71" TYPE="SINGLE_PAGE">
                <ns3:fptr>
                    <ns3:area FILEID="PAGEXML_71"/>
                </ns3:fptr>
            </ns3:div>
            <ns3:div ID="PAGE_72" ORDER="72" TYPE="SINGLE_PAGE">
                <ns3:fptr>
                    <ns3:area FILEID="PAGEXML_72"/>
                </ns3:fptr>
            </ns3:div>
            <ns3:div ID="PAGE_73" ORDER="73" TYPE="SINGLE_PAGE">
                <ns3:fptr>
                    <ns3:area FILEID="PAGEXML_73"/>
                </ns3:fptr>
            </ns3:div>
            <ns3:div ID="PAGE_74" ORDER="74" TYPE="SINGLE_PAGE">
                <ns3:fptr>
                    <ns3:area FILEID="PAGEXML_74"/>
                </ns3:fptr>
            </ns3:div>
            <ns3:div ID="PAGE_75" ORDER="75" TYPE="SINGLE_PAGE">
                <ns3:fptr>
                    <ns3:area FILEID="PAGEXML_75"/>
                </ns3:fptr>
            </ns3:div>
            <ns3:div ID="PAGE_76" ORDER="76" TYPE="SINGLE_PAGE">
                <ns3:fptr>
                    <ns3:area FILEID="PAGEXML_76"/>
                </ns3:fptr>
            </ns3:div>
            <ns3:div ID="PAGE_77" ORDER="77" TYPE="SINGLE_PAGE">
                <ns3:fptr>
                    <ns3:area FILEID="PAGEXML_77"/>
                </ns3:fptr>
            </ns3:div>
            <ns3:div ID="PAGE_78" ORDER="78" TYPE="SINGLE_PAGE">
                <ns3:fptr>
                    <ns3:area FILEID="PAGEXML_78"/>
                </ns3:fptr>
            </ns3:div>
            <ns3:div ID="PAGE_79" ORDER="79" TYPE="SINGLE_PAGE">
                <ns3:fptr>
                    <ns3:area FILEID="PAGEXML_79"/>
                </ns3:fptr>
            </ns3:div>
            <ns3:div ID="PAGE_80" ORDER="80" TYPE="SINGLE_PAGE">
                <ns3:fptr>
                    <ns3:area FILEID="PAGEXML_80"/>
                </ns3:fptr>
            </ns3:div>
            <ns3:div ID="PAGE_81" ORDER="81" TYPE="SINGLE_PAGE">
                <ns3:fptr>
                    <ns3:area FILEID="PAGEXML_81"/>
                </ns3:fptr>
            </ns3:div>
            <ns3:div ID="PAGE_82" ORDER="82" TYPE="SINGLE_PAGE">
                <ns3:fptr>
                    <ns3:area FILEID="PAGEXML_82"/>
                </ns3:fptr>
            </ns3:div>
            <ns3:div ID="PAGE_83" ORDER="83" TYPE="SINGLE_PAGE">
                <ns3:fptr>
                    <ns3:area FILEID="PAGEXML_83"/>
                </ns3:fptr>
            </ns3:div>
            <ns3:div ID="PAGE_84" ORDER="84" TYPE="SINGLE_PAGE">
                <ns3:fptr>
                    <ns3:area FILEID="PAGEXML_84"/>
                </ns3:fptr>
            </ns3:div>
            <ns3:div ID="PAGE_85" ORDER="85" TYPE="SINGLE_PAGE">
                <ns3:fptr>
                    <ns3:area FILEID="PAGEXML_85"/>
                </ns3:fptr>
            </ns3:div>
            <ns3:div ID="PAGE_86" ORDER="86" TYPE="SINGLE_PAGE">
                <ns3:fptr>
                    <ns3:area FILEID="PAGEXML_86"/>
                </ns3:fptr>
            </ns3:div>
            <ns3:div ID="PAGE_87" ORDER="87" TYPE="SINGLE_PAGE">
                <ns3:fptr>
                    <ns3:area FILEID="PAGEXML_87"/>
                </ns3:fptr>
            </ns3:div>
            <ns3:div ID="PAGE_88" ORDER="88" TYPE="SINGLE_PAGE">
                <ns3:fptr>
                    <ns3:area FILEID="PAGEXML_88"/>
                </ns3:fptr>
            </ns3:div>
            <ns3:div ID="PAGE_89" ORDER="89" TYPE="SINGLE_PAGE">
                <ns3:fptr>
                    <ns3:area FILEID="PAGEXML_89"/>
                </ns3:fptr>
            </ns3:div>
            <ns3:div ID="PAGE_90" ORDER="90" TYPE="SINGLE_PAGE">
                <ns3:fptr>
                    <ns3:area FILEID="PAGEXML_90"/>
                </ns3:fptr>
            </ns3:div>
            <ns3:div ID="PAGE_91" ORDER="91" TYPE="SINGLE_PAGE">
                <ns3:fptr>
                    <ns3:area FILEID="PAGEXML_91"/>
                </ns3:fptr>
            </ns3:div>
            <ns3:div ID="PAGE_92" ORDER="92" TYPE="SINGLE_PAGE">
                <ns3:fptr>
                    <ns3:area FILEID="PAGEXML_92"/>
                </ns3:fptr>
            </ns3:div>
            <ns3:div ID="PAGE_93" ORDER="93" TYPE="SINGLE_PAGE">
                <ns3:fptr>
                    <ns3:area FILEID="PAGEXML_93"/>
                </ns3:fptr>
            </ns3:div>
            <ns3:div ID="PAGE_94" ORDER="94" TYPE="SINGLE_PAGE">
                <ns3:fptr>
                    <ns3:area FILEID="PAGEXML_94"/>
                </ns3:fptr>
            </ns3:div>
            <ns3:div ID="PAGE_95" ORDER="95" TYPE="SINGLE_PAGE">
                <ns3:fptr>
                    <ns3:area FILEID="PAGEXML_95"/>
                </ns3:fptr>
            </ns3:div>
            <ns3:div ID="PAGE_96" ORDER="96" TYPE="SINGLE_PAGE">
                <ns3:fptr>
                    <ns3:area FILEID="PAGEXML_96"/>
                </ns3:fptr>
            </ns3:div>
            <ns3:div ID="PAGE_97" ORDER="97" TYPE="SINGLE_PAGE">
                <ns3:fptr>
                    <ns3:area FILEID="PAGEXML_97"/>
                </ns3:fptr>
            </ns3:div>
            <ns3:div ID="PAGE_98" ORDER="98" TYPE="SINGLE_PAGE">
                <ns3:fptr>
                    <ns3:area FILEID="PAGEXML_98"/>
                </ns3:fptr>
            </ns3:div>
            <ns3:div ID="PAGE_99" ORDER="99" TYPE="SINGLE_PAGE">
                <ns3:fptr>
                    <ns3:area FILEID="PAGEXML_99"/>
                </ns3:fptr>
            </ns3:div>
        </ns3:div>
    </ns3:structMap>
</ns3:mets>
